{
  "matchIndex": 297,
  "rounds": [
    {
      "roundIndex": 1,
      "result": "loss",
      "gold": 37,
      "items": {
        "Relic Case": 1,
        "Leather Bag": 2,
        "Walrus Tusk": 1,
        "Whetstone": 1,
        "Broom": 1,
        "Lump of Coal": 1,
        "Wooden Sword": 1
      }
    },
    {
      "roundIndex": 2,
      "result": "win",
      "gold": 51,
      "items": {
        "Relic Case": 1,
        "Leather Bag": 3,
        "Fanny Pack": 1,
        "Shepherd’s Crook": 1,
        "Torch": 1,
        "Piggybank": 1,
        "Walrus Tusk": 1,
        "Gloves of Haste": 1
      }
    },
    {
      "roundIndex": 3,
      "result": "win",
      "gold": 69,
      "items": {
        "Relic Case": 1,
        "Leather Bag": 4,
        "Fanny Pack": 1,
        "Shepherd’s Crook": 1,
        "Torch": 1,
        "Piggybank": 2,
        "Claws of Attack": 1,
        "Goobling": 2,
        "It’s Slime Time!": 1,
        "Blueberries": 1
      }
    },
    {
      "roundIndex": 4,
      "result": "win",
      "gold": 88,
      "items": {
        "Leather Bag": 5,
        "Relic Case": 1,
        "Fanny Pack": 1,
        "Shepherd’s Crook": 1,
        "Goobert": 1,
        "Torch": 1,
        "Claws of Attack": 1,
        "It’s Slime Time!": 1,
        "Blueberries": 1,
        "Leather Armor": 1,
        "Piggybank": 2,
        "Amulet of Darkness": 1
      }
    },
    {
      "roundIndex": 5,
      "result": "win",
      "gold": 99,
      "items": {
        "Relic Case": 1,
        "Leather Bag": 5,
        "Fanny Pack": 1,
        "Holdall": 1,
        "Goobert": 1,
        "It’s Slime Time!": 1,
        "Blueberries": 1,
        "Shepherd’s Crook": 1,
        "Torch": 1,
        "Claws of Attack": 1,
        "Toad": 1,
        "Amulet of Darkness": 1,
        "Box of Riches": 1,
        "Piggybank": 2
      }
    },
    {
      "roundIndex": 6,
      "result": "win",
      "gold": 116,
      "items": {
        "Relic Case": 1,
        "Leather Bag": 5,
        "Fanny Pack": 1,
        "Holdall": 1,
        "Goobert": 1,
        "It’s Slime Time!": 1,
        "Blueberries": 1,
        "Toad": 1,
        "Shepherd’s Crook": 1,
        "Flawed Sapphire": 1,
        "Torch": 1,
        "Claws of Attack": 1,
        "Hungry Blade": 1,
        "Piggybank": 2,
        "Box of Riches": 1,
        "Chipped Topaz": 1,
        "Cap of Resilience": 1,
        "Amulet of Darkness": 1
      }
    },
    {
      "roundIndex": 7,
      "result": "loss",
      "gold": 129,
      "items": {
        "Relic Case": 1,
        "Leather Bag": 5,
        "Fanny Pack": 1,
        "Holdall": 1,
        "Goobert": 1,
        "It’s Slime Time!": 1,
        "Blueberries": 1,
        "Toad": 1,
        "Shepherd’s Crook": 1,
        "Flawed Sapphire": 1,
        "Torch": 1,
        "Chipped Ruby": 1,
        "Claws of Attack": 1,
        "Hungry Blade": 1,
        "Piggybank": 2,
        "Box of Riches": 1,
        "Amulet of Darkness": 1,
        "Glowing Crown": 1,
        "Chipped Topaz": 1,
        "Cap of Resilience": 1
      }
    },
    {
      "roundIndex": 8,
      "result": "loss",
      "gold": 148,
      "items": {
        "Relic Case": 1,
        "Leather Bag": 5,
        "Fanny Pack": 1,
        "Holdall": 1,
        "Stamina Sack": 1,
        "Potion Belt": 1,
        "Goobert": 1,
        "It’s Slime Time!": 1,
        "Blueberries": 1,
        "Toad": 1,
        "Flawed Sapphire": 1,
        "Torch": 1,
        "Chipped Ruby": 1,
        "Claws of Attack": 1,
        "Hungry Blade": 1,
        "Piggybank": 2,
        "Cap of Resilience": 1,
        "Chipped Sapphire": 1,
        "Chipped Topaz": 1,
        "King Crown": 1,
        "Health Potion": 1,
        "Shepherd’s Crook": 1,
        "Nocturnal Lock Lifter": 1
      }
    },
    {
      "roundIndex": 9,
      "result": "win",
      "gold": 159,
      "items": {
        "Relic Case": 1,
        "Leather Bag": 5,
        "Fanny Pack": 1,
        "Holdall": 1,
        "Stamina Sack": 1,
        "Potion Belt": 1,
        "It’s Slime Time!": 1,
        "Hungry Blade": 1,
        "Piggybank": 2,
        "Shepherd’s Crook": 1,
        "Nocturnal Lock Lifter": 1,
        "Chipped Sapphire": 1,
        "Chipped Topaz": 1,
        "King Goobert": 1,
        "Flawed Sapphire": 1,
        "Torch": 1,
        "Chipped Ruby": 1,
        "Claws of Attack": 1,
        "Mana Potion": 1,
        "Toad": 1,
        "Jynx torquilla": 1,
        "Cap of Resilience": 1,
        "Deck of Cards": 1
      }
    },
    {
      "roundIndex": 10,
      "result": "win",
      "gold": 176,
      "items": {
        "Relic Case": 1,
        "Leather Bag": 5,
        "Fanny Pack": 1,
        "Holdall": 1,
        "Potion Belt": 1,
        "Stamina Sack": 2,
        "Hungry Blade": 1,
        "Piggybank": 2,
        "Shepherd’s Crook": 1,
        "Nocturnal Lock Lifter": 1,
        "Chipped Ruby": 1,
        "Claws of Attack": 1,
        "Flawed Sapphire": 1,
        "Magic Torch": 1,
        "Chipped Sapphire": 1,
        "Chipped Topaz": 1,
        "King Goobert": 1,
        "Cap of Resilience": 2,
        "Jynx torquilla": 1,
        "Mana Mastery": 1,
        "Toad": 1,
        "It’s Slime Time!": 1,
        "Deck of Cards": 1
      }
    },
    {
      "roundIndex": 11,
      "result": "win",
      "gold": 194,
      "items": {
        "Relic Case": 1,
        "Leather Bag": 5,
        "Fanny Pack": 1,
        "Holdall": 1,
        "Potion Belt": 1,
        "Stamina Sack": 2,
        "Nocturnal Lock Lifter": 1,
        "Flawed Sapphire": 1,
        "Magic Torch": 1,
        "Chipped Sapphire": 1,
        "Chipped Topaz": 1,
        "King Goobert": 1,
        "Jynx torquilla": 1,
        "Toad": 1,
        "It’s Slime Time!": 1,
        "Deck of Cards": 1,
        "Shepherd’s Crook": 1,
        "Hungry Blade": 1,
        "Chipped Ruby": 1,
        "Claws of Attack": 1,
        "Mana Orb": 1,
        "Piggybank": 2,
        "Darkest Lotus": 1,
        "Cap of Resilience": 2,
        "Stone Skin Potion": 1,
        "Mana Mastery": 1
      }
    },
    {
      "roundIndex": 12,
      "result": "win",
      "gold": 211,
      "items": {
        "Relic Case": 1,
        "Leather Bag": 5,
        "Fanny Pack": 1,
        "Holdall": 1,
        "Potion Belt": 1,
        "Stamina Sack": 2,
        "Nocturnal Lock Lifter": 1,
        "Flawed Sapphire": 1,
        "Magic Torch": 1,
        "Chipped Sapphire": 1,
        "Chipped Topaz": 1,
        "King Goobert": 1,
        "Jynx torquilla": 1,
        "Toad": 1,
        "It’s Slime Time!": 1,
        "Deck of Cards": 1,
        "Shepherd’s Crook": 1,
        "Piggybank": 2,
        "Mana Mastery": 1,
        "Stone Helm": 1,
        "Corrupted Crystal": 1,
        "Cap of Resilience": 1,
        "Chipped Ruby": 1,
        "Manathirst": 1,
        "Hungry Blade": 1,
        "Mana Orb": 1,
        "Holo Fire Lizard": 1,
        "Darkest Lotus": 1
      }
    },
    {
      "roundIndex": 13,
      "result": "loss",
      "gold": 226,
      "items": {
        "Relic Case": 1,
        "Leather Bag": 5,
        "Fanny Pack": 1,
        "Holdall": 1,
        "Potion Belt": 2,
        "Stamina Sack": 3,
        "Nocturnal Lock Lifter": 1,
        "Flawed Sapphire": 1,
        "Magic Torch": 1,
        "Chipped Sapphire": 1,
        "Chipped Topaz": 1,
        "King Goobert": 1,
        "Jynx torquilla": 1,
        "Toad": 1,
        "Deck of Cards": 1,
        "Shepherd’s Crook": 1,
        "Piggybank": 2,
        "Stone Helm": 1,
        "Chipped Ruby": 1,
        "Manathirst": 2,
        "Holo Fire Lizard": 2,
        "Cap of Discomfort": 1,
        "Darkest Lotus": 1,
        "Mana Mastery": 1,
        "It’s Slime Time!": 1
      }
    },
    {
      "roundIndex": 14,
      "result": "win",
      "gold": 236,
      "items": {
        "Relic Case": 1,
        "Leather Bag": 5,
        "Fanny Pack": 1,
        "Holdall": 1,
        "Potion Belt": 2,
        "Stamina Sack": 3,
        "Nocturnal Lock Lifter": 1,
        "Flawed Sapphire": 1,
        "Magic Torch": 1,
        "Chipped Sapphire": 1,
        "Chipped Topaz": 1,
        "King Goobert": 1,
        "Jynx torquilla": 1,
        "Deck of Cards": 1,
        "Piggybank": 2,
        "Stone Helm": 1,
        "Chipped Ruby": 1,
        "Manathirst": 2,
        "Holo Fire Lizard": 2,
        "Darkest Lotus": 1,
        "Mana Mastery": 1,
        "Cap of Discomfort": 1,
        "It’s Slime Time!": 1,
        "Toad": 1,
        "Snowcake": 1,
        "Wolpertinger": 1
      }
    },
    {
      "roundIndex": 15,
      "result": "win",
      "gold": 249,
      "items": {
        "Relic Case": 1,
        "Leather Bag": 5,
        "Fanny Pack": 1,
        "Holdall": 1,
        "Potion Belt": 2,
        "Stamina Sack": 3,
        "Nocturnal Lock Lifter": 1,
        "Flawed Sapphire": 1,
        "Magic Torch": 1,
        "Chipped Sapphire": 1,
        "Chipped Topaz": 1,
        "King Goobert": 1,
        "Jynx torquilla": 1,
        "Piggybank": 1,
        "Chipped Ruby": 1,
        "Manathirst": 2,
        "Mana Mastery": 1,
        "Toad": 1,
        "Snowcake": 1,
        "It’s Slime Time!": 1,
        "Wolpertinger": 1,
        "Djinn Lamp": 1,
        "Stone Helm": 1,
        "Deck of Cards": 1,
        "Holo Fire Lizard": 2,
        "Cap of Discomfort": 1,
        "Darkest Lotus": 1,
        "Jimbo": 1
      }
    },
    {
      "roundIndex": 16,
      "result": "loss",
      "gold": 273,
      "items": {
        "Relic Case": 1,
        "Leather Bag": 5,
        "Fanny Pack": 1,
        "Holdall": 1,
        "Potion Belt": 3,
        "Stamina Sack": 3,
        "Nocturnal Lock Lifter": 1,
        "Flawed Sapphire": 1,
        "Magic Torch": 1,
        "Chipped Sapphire": 1,
        "Chipped Topaz": 1,
        "King Goobert": 1,
        "Jynx torquilla": 1,
        "Piggybank": 1,
        "Chipped Ruby": 1,
        "Manathirst": 2,
        "Mana Mastery": 1,
        "Toad": 1,
        "Wolpertinger": 1,
        "Djinn Lamp": 1,
        "Stone Helm": 1,
        "Deck of Cards": 1,
        "Holo Fire Lizard": 3,
        "Cap of Discomfort": 1,
        "Jimbo": 1,
        "Darkest Lotus": 1,
        "Snowcake": 1,
        "Prismatic Orb": 1,
        "It’s Slime Time!": 1
      }
    },
    {
      "roundIndex": 17,
      "result": "win",
      "gold": 292,
      "items": {
        "Relic Case": 1,
        "Leather Bag": 5,
        "Fanny Pack": 1,
        "Holdall": 1,
        "Potion Belt": 4,
        "Stamina Sack": 3,
        "Nocturnal Lock Lifter": 1,
        "Flawed Sapphire": 1,
        "Magic Torch": 1,
        "Chipped Sapphire": 1,
        "Chipped Topaz": 1,
        "King Goobert": 1,
        "Chipped Ruby": 1,
        "Manathirst": 2,
        "Djinn Lamp": 1,
        "Cap of Discomfort": 1,
        "Deck of Cards": 1,
        "Holo Fire Lizard": 3,
        "Mana Mastery": 1,
        "Jimbo": 2,
        "Paradise Birb": 1,
        "Stone Helm": 1,
        "Mana Orb": 1,
        "Darkest Lotus": 2,
        "Snowcake": 1,
        "Wolpertinger": 1,
        "Toad": 1,
        "It’s Slime Time!": 1
      }
    },
    {
      "roundIndex": 18,
      "result": "win",
      "gold": 308,
      "items": {
        "Relic Case": 1,
        "Leather Bag": 5,
        "Potion Belt": 4,
        "Stamina Sack": 4,
        "Holdall": 1,
        "Fanny Pack": 1,
        "Chipped Sapphire": 1,
        "Chipped Topaz": 1,
        "King Goobert": 1,
        "Djinn Lamp": 1,
        "Cap of Discomfort": 1,
        "Deck of Cards": 1,
        "Holo Fire Lizard": 4,
        "Jimbo": 2,
        "Paradise Birb": 1,
        "Mana Orb": 2,
        "Wolpertinger": 1,
        "Toad": 1,
        "It’s Slime Time!": 1,
        "Darkest Lotus": 2,
        "Mana Mastery": 1,
        "Snowcake": 1,
        "Chipped Ruby": 1,
        "Manathirst": 2,
        "Flawed Sapphire": 1,
        "Magic Torch": 1,
        "Nocturnal Lock Lifter": 1,
        "Stone Helm": 1
      }
    }
  ]
}