{
  "matchIndex": 426,
  "rounds": [
    {
      "roundIndex": 1,
      "result": "loss",
      "gold": 38,
      "items": {
        "Storage Coffin": 1,
        "Leather Bag": 1,
        "Broom": 1,
        "Pan": 1,
        "Fly Agaric": 1,
        "Piggybank": 1
      }
    },
    {
      "roundIndex": 2,
      "result": "loss",
      "gold": 50,
      "items": {
        "Storage Coffin": 1,
        "Leather Bag": 2,
        "Fly Agaric": 1,
        "Shovel": 1,
        "Wooden Sword": 1,
        "Shiny Shell": 1,
        "Banana": 1,
        "Piggybank": 1
      }
    },
    {
      "roundIndex": 3,
      "result": "win",
      "gold": 77,
      "items": {
        "Leather Bag": 4,
        "Storage Coffin": 1,
        "Shovel": 1,
        "Shell Totem": 1,
        "Goobert": 1,
        "Fly Agaric": 2,
        "Piggybank": 1,
        "Gloves of Haste": 1,
        "Banana": 1,
        "Mushroom Farm": 1,
        "Stone": 1
      }
    },
    {
      "roundIndex": 4,
      "result": "win",
      "gold": 91,
      "items": {
        "Leather Bag": 5,
        "Storage Coffin": 1,
        "Shovel": 1,
        "Shell Totem": 1,
        "Piggybank": 1,
        "Gloves of Haste": 1,
        "Poison Goobert": 1,
        "Fly Agaric": 1,
        "Shiny Shell": 1,
        "Banana": 1,
        "Stone": 1,
        "Mushroom Farm": 1,
        "Box of Riches": 1
      }
    },
    {
      "roundIndex": 5,
      "result": "win",
      "gold": 103,
      "items": {
        "Leather Bag": 6,
        "Storage Coffin": 1,
        "Stone Skin Potion": 1,
        "Poison Goobert": 1,
        "Chipped Emerald": 1,
        "Shovel": 1,
        "Mushroom Farm": 1,
        "Fly Agaric": 1,
        "Shell Totem": 1,
        "Shiny Shell": 1,
        "Gloves of Haste": 1,
        "Banana": 1,
        "Box of Riches": 1,
        "Chipped Topaz": 1,
        "Piggybank": 1,
        "Stone": 1
      }
    },
    {
      "roundIndex": 6,
      "result": "win",
      "gold": 120,
      "items": {
        "Leather Bag": 6,
        "Storage Coffin": 1,
        "Stamina Sack": 1,
        "Gloves of Haste": 1,
        "Chipped Emerald": 1,
        "Shovel": 1,
        "Poison Goobert": 1,
        "Fly Agaric": 2,
        "Mushroom Farm": 1,
        "Shell Totem": 1,
        "Banana": 1,
        "Blueberries": 1,
        "Flute": 1,
        "Box of Riches": 1,
        "Shiny Shell": 1,
        "Piggybank": 1,
        "Stone Skin Potion": 1,
        "Stone": 1,
        "Chipped Sapphire": 1,
        "Chipped Topaz": 1
      }
    },
    {
      "roundIndex": 7,
      "result": "loss",
      "gold": 135,
      "items": {
        "Leather Bag": 6,
        "Storage Coffin": 1,
        "Stamina Sack": 1,
        "Fanny Pack": 2,
        "Poison Goobert": 1,
        "Fly Agaric": 3,
        "Shell Totem": 1,
        "Banana": 1,
        "Blueberries": 1,
        "Box of Riches": 1,
        "Shiny Shell": 1,
        "Chipped Topaz": 1,
        "Chipped Emerald": 2,
        "Shovel": 1,
        "Gloves of Haste": 1,
        "Flute": 1,
        "Mushroom Farm": 1,
        "Piggybank": 1,
        "Toad": 1,
        "Stone Skin Potion": 1,
        "Chipped Sapphire": 1
      }
    },
    {
      "roundIndex": 8,
      "result": "win",
      "gold": 149,
      "items": {
        "Storage Coffin": 1,
        "Stamina Sack": 1,
        "Fanny Pack": 3,
        "Leather Bag": 6,
        "Shell Totem": 1,
        "Poison Goobert": 1,
        "Snake": 1,
        "Poison Frog": 1,
        "Jynx torquilla": 1,
        "Fly Agaric": 3,
        "Mushroom Farm": 1,
        "Blueberries": 1,
        "Chipped Emerald": 3,
        "Shovel": 1,
        "Banana": 1,
        "Gloves of Haste": 1,
        "Cap of Resilience": 1,
        "Box of Riches": 1,
        "Chipped Topaz": 1
      }
    },
    {
      "roundIndex": 9,
      "result": "loss",
      "gold": 180,
      "items": {
        "Storage Coffin": 1,
        "Stamina Sack": 1,
        "Fanny Pack": 3,
        "Leather Bag": 7,
        "Potion Belt": 1,
        "Shell Totem": 1,
        "Poison Goobert": 1,
        "Snake": 1,
        "Poison Frog": 1,
        "Chipped Emerald": 3,
        "Jynx torquilla": 1,
        "Toad": 1,
        "Shovel": 1,
        "Fly Agaric": 4,
        "Mushroom Farm": 1,
        "Blueberries": 1,
        "Chipped Topaz": 1,
        "Leather Armor": 1,
        "Cap of Resilience": 1,
        "Gloves of Haste": 1,
        "Banana": 1,
        "Stone Skin Potion": 1,
        "Box of Riches": 1
      }
    },
    {
      "roundIndex": 10,
      "result": "win",
      "gold": 205,
      "items": {
        "Storage Coffin": 1,
        "Stamina Sack": 1,
        "Fanny Pack": 3,
        "Leather Bag": 7,
        "Potion Belt": 1,
        "Snake": 1,
        "Poison Frog": 1,
        "Jynx torquilla": 1,
        "Fly Agaric": 5,
        "Mushroom Farm": 1,
        "Toad": 1,
        "Blueberries": 1,
        "Poison Goobert": 1,
        "Perfect Amethyst": 1,
        "Chipped Ruby": 1,
        "Chipped Topaz": 1,
        "Death Scythe": 1,
        "Chipped Emerald": 2,
        "Stone Armor": 1,
        "Corrupted Crystal": 1,
        "Cap of Resilience": 1,
        "Gloves of Haste": 1,
        "Banana": 1,
        "Stoned": 1
      }
    },
    {
      "roundIndex": 11,
      "result": "win",
      "gold": 222,
      "items": {
        "Storage Coffin": 1,
        "Stamina Sack": 2,
        "Fanny Pack": 3,
        "Leather Bag": 7,
        "Potion Belt": 2,
        "Snake": 1,
        "Jynx torquilla": 1,
        "Poison Goobert": 1,
        "Chipped Emerald": 3,
        "Cap of Discomfort": 1,
        "Poison Frog": 2,
        "Perfect Amethyst": 1,
        "Chipped Ruby": 1,
        "Chipped Topaz": 1,
        "Death Scythe": 1,
        "Gloves of Haste": 1,
        "Fly Agaric": 6,
        "Blueberries": 1,
        "Stoned": 1,
        "Stone Armor": 1,
        "Banana": 1,
        "Mushroom Farm": 1
      }
    },
    {
      "roundIndex": 12,
      "result": "win",
      "gold": 239,
      "items": {
        "Storage Coffin": 1,
        "Stamina Sack": 2,
        "Fanny Pack": 3,
        "Leather Bag": 7,
        "Potion Belt": 2,
        "Snake": 1,
        "Jynx torquilla": 1,
        "Poison Goobert": 1,
        "Chipped Emerald": 3,
        "Cap of Discomfort": 1,
        "Poison Frog": 2,
        "Fly Agaric": 7,
        "Stoned": 1,
        "Corrupted Crystal": 1,
        "Cap of Resilience": 1,
        "Perfect Amethyst": 1,
        "Chipped Ruby": 1,
        "Chipped Topaz": 1,
        "Death Scythe": 1,
        "Gloves of Haste": 1,
        "Stone Armor": 1,
        "Mushroom Farm": 1,
        "Blueberries": 1,
        "Banana": 1
      }
    },
    {
      "roundIndex": 13,
      "result": "win",
      "gold": 251,
      "items": {
        "Storage Coffin": 1,
        "Stamina Sack": 3,
        "Fanny Pack": 3,
        "Leather Bag": 8,
        "Potion Belt": 2,
        "Snake": 1,
        "Jynx torquilla": 1,
        "Poison Goobert": 1,
        "Chipped Emerald": 3,
        "Cap of Discomfort": 2,
        "Poison Frog": 2,
        "Fly Agaric": 8,
        "Perfect Amethyst": 1,
        "Chipped Ruby": 1,
        "Chipped Topaz": 1,
        "Death Scythe": 1,
        "Mushroom Farm": 1,
        "Blueberries": 1,
        "Banana": 1,
        "Gloves of Haste": 1,
        "Stone Armor": 1,
        "Stoned": 1
      }
    },
    {
      "roundIndex": 14,
      "result": "win",
      "gold": 269,
      "items": {
        "Storage Coffin": 1,
        "Stamina Sack": 3,
        "Fanny Pack": 3,
        "Leather Bag": 8,
        "Potion Belt": 2,
        "Snake": 1,
        "Jynx torquilla": 1,
        "Poison Goobert": 1,
        "Chipped Emerald": 3,
        "Cap of Discomfort": 2,
        "Poison Frog": 2,
        "Fly Agaric": 10,
        "Perfect Amethyst": 1,
        "Chipped Ruby": 1,
        "Chipped Topaz": 1,
        "Death Scythe": 1,
        "Mushroom Farm": 1,
        "Blueberries": 1,
        "Gloves of Haste": 1,
        "Stone Armor": 1,
        "Stoned": 1,
        "Fancy Fencing Rapier": 1,
        "Banana": 1
      }
    },
    {
      "roundIndex": 15,
      "result": "win",
      "gold": 275,
      "items": {
        "Storage Coffin": 1,
        "Stamina Sack": 3,
        "Fanny Pack": 3,
        "Leather Bag": 8,
        "Potion Belt": 2,
        "Snake": 1,
        "Jynx torquilla": 1,
        "Poison Goobert": 1,
        "Chipped Emerald": 3,
        "Cap of Discomfort": 2,
        "Poison Frog": 2,
        "Fly Agaric": 10,
        "Perfect Amethyst": 1,
        "Chipped Ruby": 1,
        "Chipped Topaz": 1,
        "Death Scythe": 1,
        "Blueberries": 1,
        "Stone Armor": 1,
        "Fancy Fencing Rapier": 1,
        "Banana": 1,
        "Gloves of Haste": 1,
        "Mushroom Farm": 1,
        "Stoned": 1,
        "Heroic Potion": 1
      }
    },
    {
      "roundIndex": 16,
      "result": "win",
      "gold": 283,
      "items": {
        "Storage Coffin": 1,
        "Stamina Sack": 3,
        "Fanny Pack": 3,
        "Leather Bag": 8,
        "Potion Belt": 2,
        "Snake": 1,
        "Jynx torquilla": 1,
        "Poison Goobert": 1,
        "Chipped Emerald": 3,
        "Cap of Discomfort": 2,
        "Poison Frog": 2,
        "Fly Agaric": 12,
        "Perfect Amethyst": 1,
        "Chipped Ruby": 1,
        "Chipped Topaz": 1,
        "Death Scythe": 1,
        "Stone Armor": 1,
        "Gloves of Haste": 1,
        "Stoned": 1,
        "Glowing Crown": 1,
        "Mushroom Farm": 1,
        "Blueberries": 2,
        "Strong Heroic Potion": 1
      }
    },
    {
      "roundIndex": 17,
      "result": "loss",
      "gold": 292,
      "items": {
        "Storage Coffin": 1,
        "Stamina Sack": 3,
        "Fanny Pack": 3,
        "Leather Bag": 8,
        "Potion Belt": 2,
        "Snake": 1,
        "Jynx torquilla": 1,
        "Poison Goobert": 1,
        "Chipped Emerald": 3,
        "Cap of Discomfort": 2,
        "Poison Frog": 2,
        "Fly Agaric": 11,
        "Perfect Amethyst": 1,
        "Chipped Ruby": 1,
        "Chipped Topaz": 1,
        "Death Scythe": 1,
        "Stone Armor": 1,
        "Gloves of Haste": 1,
        "Stoned": 1,
        "Glowing Crown": 2,
        "Mushroom Farm": 1,
        "Blueberries": 2,
        "Strong Heroic Potion": 1
      }
    },
    {
      "roundIndex": 18,
      "result": "win",
      "gold": 292,
      "items": {
        "Storage Coffin": 1,
        "Stamina Sack": 3,
        "Fanny Pack": 3,
        "Leather Bag": 8,
        "Potion Belt": 2,
        "Snake": 1,
        "Jynx torquilla": 1,
        "Poison Goobert": 1,
        "Chipped Emerald": 3,
        "Cap of Discomfort": 2,
        "Poison Frog": 2,
        "Fly Agaric": 11,
        "Perfect Amethyst": 1,
        "Chipped Ruby": 1,
        "Chipped Topaz": 1,
        "Death Scythe": 1,
        "Stone Armor": 1,
        "Gloves of Haste": 1,
        "Stoned": 1,
        "Glowing Crown": 2,
        "Mushroom Farm": 1,
        "Blueberries": 2,
        "Strong Heroic Potion": 1
      }
    }
  ]
}