{
  "matchIndex": 713,
  "rounds": [
    {
      "roundIndex": 1,
      "result": "loss",
      "gold": 43,
      "items": {
        "Relic Case": 1,
        "Fanny Pack": 1,
        "Leather Bag": 1,
        "Leaf Badge": 1,
        "Pan": 1,
        "Amulet of Fortune": 1,
        "Wooden Sword": 1,
        "Garlic": 1,
        "Healing Herbs": 1
      }
    },
    {
      "roundIndex": 2,
      "result": "loss",
      "gold": 52,
      "items": {
        "Relic Case": 1,
        "Fanny Pack": 1,
        "Leather Bag": 2,
        "Amulet of Fortune": 1,
        "Garlic": 1,
        "Lump of Coal": 1,
        "Wooden Sword": 1,
        "Shortbow": 1,
        "Leaf Badge": 1,
        "Stone": 1,
        "Amulet of Steel": 1
      }
    },
    {
      "roundIndex": 3,
      "result": "win",
      "gold": 64,
      "items": {
        "Relic Case": 1,
        "Fanny Pack": 1,
        "Leather Bag": 2,
        "Lump of Coal": 1,
        "Flame Badge": 1,
        "Thorn Whip": 1,
        "Leaf Badge": 1,
        "Amulet of Fortune": 1,
        "Uniquely Unique": 1,
        "Amulet of Steel": 1,
        "Stone": 1,
        "Fly Agaric": 1
      }
    },
    {
      "roundIndex": 4,
      "result": "win",
      "gold": 74,
      "items": {
        "Relic Case": 1,
        "Fanny Pack": 1,
        "Leather Bag": 3,
        "Flame Badge": 1,
        "Lump of Coal": 1,
        "Thorn Whip": 1,
        "Leaf Badge": 1,
        "Amulet of Fortune": 1,
        "Uniquely Unique": 1,
        "Amulet of Steel": 1,
        "Fly Agaric": 1,
        "Garlic": 1,
        "Carrot": 1,
        "Flame": 1,
        "Stone": 1
      }
    },
    {
      "roundIndex": 5,
      "result": "win",
      "gold": 80,
      "items": {
        "Relic Case": 1,
        "Fanny Pack": 1,
        "Leather Bag": 3,
        "Leaf Badge": 1,
        "Amulet of Fortune": 1,
        "Present": 1,
        "Burning Coal": 1,
        "Thorn Whip": 1,
        "Uniquely Unique": 1,
        "Carrot": 1,
        "Fly Agaric": 1,
        "Amulet of Steel": 1,
        "Flame Badge": 1
      }
    },
    {
      "roundIndex": 6,
      "result": "win",
      "gold": 101,
      "items": {
        "Relic Case": 1,
        "Fanny Pack": 1,
        "Leather Bag": 3,
        "Puzzlebag of Ruin": 1,
        "Leaf Badge": 1,
        "Amulet of Fortune": 1,
        "Present": 1,
        "Carrot": 1,
        "Fly Agaric": 1,
        "Amulet of Steel": 1,
        "Burning Coal": 1,
        "Thorn Whip": 1,
        "Uniquely Unique": 1,
        "Stone Shoes": 1,
        "Flame Badge": 1,
        "Dragon Claws": 1
      }
    },
    {
      "roundIndex": 7,
      "result": "win",
      "gold": 121,
      "items": {
        "Relic Case": 1,
        "Fanny Pack": 1,
        "Leather Bag": 3,
        "Puzzlebag of Ruin": 1,
        "Stamina Sack": 1,
        "Present": 1,
        "Carrot": 1,
        "Fly Agaric": 1,
        "Regular Amethyst": 1,
        "Stone Shoes": 1,
        "Dragon Claws": 1,
        "Burning Coal": 1,
        "Fancy Fencing Rapier": 1,
        "Leaf Badge": 1,
        "Amulet of Fortune": 1,
        "Amulet of Steel": 1,
        "Flame Badge": 1,
        "Flame": 2,
        "Uniquely Unique": 1,
        "Badger Spirit Companion": 1
      }
    },
    {
      "roundIndex": 8,
      "result": "win",
      "gold": 152,
      "items": {
        "Relic Case": 1,
        "Fanny Pack": 1,
        "Leather Bag": 3,
        "Puzzlebag of Ruin": 1,
        "Stamina Sack": 1,
        "Puzzlebag of Love": 1,
        "Present": 1,
        "Regular Amethyst": 1,
        "Stone Shoes": 1,
        "Dragon Claws": 1,
        "Burning Coal": 1,
        "Fancy Fencing Rapier": 1,
        "Leaf Badge": 1,
        "Amulet of Steel": 1,
        "Uniquely Unique": 1,
        "Badger Spirit Companion": 1,
        "Cheese": 1,
        "Snake": 1,
        "Hyper Hedgehog": 1,
        "Flame Badge": 1,
        "Carrot": 1,
        "Amulet of Fortune": 1
      }
    },
    {
      "roundIndex": 9,
      "result": "win",
      "gold": 182,
      "items": {
        "Relic Case": 1,
        "Fanny Pack": 1,
        "Leather Bag": 3,
        "Puzzlebag of Ruin": 1,
        "Stamina Sack": 1,
        "Potion Belt": 1,
        "Holdall": 1,
        "Puzzlebag of Love": 1,
        "Regular Amethyst": 1,
        "Stone Shoes": 1,
        "Dragon Claws": 1,
        "Burning Coal": 1,
        "Fancy Fencing Rapier": 1,
        "Amulet of Steel": 1,
        "Uniquely Unique": 1,
        "Snake": 1,
        "Leaf Badge": 1,
        "Badger Spirit Companion": 1,
        "Present": 1,
        "Flame Badge": 1,
        "Amulet of Fortune": 1,
        "Jynx torquilla": 1,
        "Hyper Hedgehog": 1,
        "Cheese": 1,
        "Rope": 1,
        "Carrot": 1,
        "Sir Sand": 1,
        "Flame": 1
      }
    },
    {
      "roundIndex": 10,
      "result": "win",
      "gold": 208,
      "items": {
        "Relic Case": 1,
        "Fanny Pack": 1,
        "Holdall": 1,
        "Leather Bag": 3,
        "Puzzlebag of Love": 1,
        "Stamina Sack": 3,
        "Puzzlebag of Ruin": 1,
        "Potion Belt": 1,
        "Flawed Topaz": 1,
        "Fancy Fencing Rapier": 1,
        "Uniquely Unique": 1,
        "Present": 1,
        "Flame Badge": 1,
        "Amulet of Fortune": 1,
        "Burning Coal": 1,
        "Leaf Badge": 1,
        "Rope": 1,
        "Dragon Claws": 1,
        "Flame": 1,
        "Snake": 1,
        "Badger Spirit Companion": 1,
        "Hyper Hedgehog": 1,
        "Jynx torquilla": 1,
        "Stoned": 1,
        "Cheese": 1,
        "Sun Shield": 1,
        "Carrot": 1,
        "Regular Amethyst": 1,
        "Stone Shoes": 1,
        "Amulet of Steel": 1
      }
    },
    {
      "roundIndex": 11,
      "result": "win",
      "gold": 223,
      "items": {
        "Relic Case": 1,
        "Fanny Pack": 1,
        "Holdall": 1,
        "Leather Bag": 3,
        "Puzzlebag of Love": 1,
        "Stamina Sack": 3,
        "Puzzlebag of Ruin": 1,
        "Potion Belt": 2,
        "Flawed Topaz": 1,
        "Fancy Fencing Rapier": 1,
        "Uniquely Unique": 1,
        "Present": 1,
        "Flame Badge": 1,
        "Amulet of Fortune": 1,
        "Burning Coal": 1,
        "Leaf Badge": 1,
        "Rope": 1,
        "Dragon Claws": 1,
        "Flame": 2,
        "Snake": 1,
        "Badger Spirit Companion": 1,
        "Hyper Hedgehog": 1,
        "Jynx torquilla": 1,
        "Stoned": 1,
        "Cheese": 1,
        "Carrot": 1,
        "Regular Amethyst": 1,
        "Stone Shoes": 1,
        "Acorn Collar": 1,
        "Amulet of Steel": 1,
        "Chipped Ruby": 1,
        "Sun Shield": 1,
        "Shiny Shell": 1
      }
    },
    {
      "roundIndex": 12,
      "result": "win",
      "gold": 240,
      "items": {
        "Relic Case": 1,
        "Fanny Pack": 1,
        "Holdall": 1,
        "Leather Bag": 4,
        "Puzzlebag of Love": 1,
        "Stamina Sack": 3,
        "Puzzlebag of Ruin": 1,
        "Potion Belt": 2,
        "Flawed Topaz": 1,
        "Fancy Fencing Rapier": 1,
        "Uniquely Unique": 1,
        "Present": 1,
        "Flame Badge": 1,
        "Amulet of Fortune": 1,
        "Burning Coal": 1,
        "Leaf Badge": 1,
        "Rope": 1,
        "Dragon Claws": 1,
        "Flame": 3,
        "Snake": 1,
        "Badger Spirit Companion": 1,
        "Hyper Hedgehog": 1,
        "Jynx torquilla": 1,
        "Stoned": 1,
        "Cheese": 1,
        "Carrot": 1,
        "Regular Amethyst": 1,
        "Stone Shoes": 1,
        "Acorn Collar": 1,
        "Cold Mirror": 1,
        "Chipped Ruby": 1,
        "Sun Shield": 1,
        "Shiny Shell": 2,
        "Amulet of Steel": 1
      }
    },
    {
      "roundIndex": 13,
      "result": "win",
      "gold": 259,
      "items": {
        "Relic Case": 1,
        "Fanny Pack": 1,
        "Holdall": 1,
        "Leather Bag": 4,
        "Puzzlebag of Love": 1,
        "Stamina Sack": 3,
        "Puzzlebag of Ruin": 1,
        "Potion Belt": 2,
        "Flawed Topaz": 1,
        "Fancy Fencing Rapier": 1,
        "Uniquely Unique": 1,
        "Present": 1,
        "Flame Badge": 1,
        "Amulet of Fortune": 1,
        "Burning Coal": 1,
        "Leaf Badge": 1,
        "Rope": 2,
        "Dragon Claws": 1,
        "Flame": 3,
        "Snake": 1,
        "Jynx torquilla": 1,
        "Stoned": 1,
        "Acorn Collar": 1,
        "Amulet of Steel": 1,
        "Hyper Hedgehog": 1,
        "Toad": 1,
        "Badger Spirit Companion": 1,
        "Cheese": 1,
        "Flawless Ruby": 1,
        "Lump of Coal": 1,
        "Sun Shield": 1,
        "Cold Mirror": 1,
        "Shiny Shell": 2,
        "Regular Amethyst": 1,
        "Stone Shoes": 1,
        "Carrot": 1
      }
    },
    {
      "roundIndex": 14,
      "result": "win",
      "gold": 275,
      "items": {
        "Relic Case": 1,
        "Fanny Pack": 1,
        "Leather Bag": 4,
        "Puzzlebag of Love": 1,
        "Stamina Sack": 4,
        "Potion Belt": 2,
        "Holdall": 1,
        "Puzzlebag of Ruin": 1,
        "Protective Purse": 1,
        "Flawed Topaz": 1,
        "Fancy Fencing Rapier": 1,
        "Uniquely Unique": 1,
        "Burning Coal": 2,
        "Leaf Badge": 1,
        "Rope": 1,
        "Dragon Claws": 1,
        "Flame": 3,
        "Stoned": 1,
        "Acorn Collar": 1,
        "Amulet of Steel": 1,
        "Badger Spirit Companion": 1,
        "Cheese": 1,
        "Flawless Ruby": 1,
        "Sun Shield": 1,
        "Cold Mirror": 1,
        "Carrot": 1,
        "Present": 1,
        "Flame Badge": 1,
        "Amulet of Fortune": 1,
        "Snake": 1,
        "Jynx torquilla": 1,
        "Toad": 1,
        "Hyper Hedgehog": 1,
        "Regular Amethyst": 1,
        "Stone Shoes": 1,
        "Shiny Shell": 2,
        "Demonic Flask": 1,
        "Unstable Recombobulator": 1
      }
    },
    {
      "roundIndex": 15,
      "result": "win",
      "gold": 297,
      "items": {
        "Relic Case": 1,
        "Fanny Pack": 1,
        "Leather Bag": 4,
        "Puzzlebag of Love": 1,
        "Stamina Sack": 4,
        "Potion Belt": 3,
        "Puzzlebag of Ruin": 1,
        "Holdall": 1,
        "Protective Purse": 1,
        "Hawk Rune": 1,
        "Fancy Fencing Rapier": 1,
        "Uniquely Unique": 1,
        "Burning Coal": 2,
        "Leaf Badge": 1,
        "Rope": 2,
        "Dragon Claws": 1,
        "Stoned": 1,
        "Acorn Collar": 1,
        "Badger Spirit Companion": 1,
        "Cheese": 1,
        "Flawless Ruby": 1,
        "Sun Shield": 1,
        "Cold Mirror": 1,
        "Flame": 6,
        "Carrot": 1,
        "Toad": 1,
        "Hyper Hedgehog": 1,
        "Shiny Shell": 2,
        "Crow": 1,
        "Flame Badge": 1,
        "Amulet of Fortune": 1,
        "Snake": 1,
        "Amulet of Steel": 1,
        "Amulet of Alchemy": 1,
        "Flawed Topaz": 1,
        "Present": 1,
        "Regular Amethyst": 1,
        "Stone Shoes": 1,
        "Cap of Resilience": 1
      }
    },
    {
      "roundIndex": 16,
      "result": "win",
      "gold": 313,
      "items": {
        "Relic Case": 1,
        "Fanny Pack": 1,
        "Leather Bag": 4,
        "Puzzlebag of Love": 1,
        "Stamina Sack": 4,
        "Potion Belt": 3,
        "Puzzlebag of Ruin": 1,
        "Holdall": 1,
        "Protective Purse": 1,
        "Hawk Rune": 1,
        "Fancy Fencing Rapier": 1,
        "Uniquely Unique": 1,
        "Burning Coal": 2,
        "Leaf Badge": 1,
        "Rope": 2,
        "Dragon Claws": 1,
        "Stoned": 1,
        "Acorn Collar": 1,
        "Badger Spirit Companion": 1,
        "Cheese": 1,
        "Flawless Ruby": 1,
        "Regular Ruby": 1,
        "Sun Shield": 1,
        "Cold Mirror": 1,
        "Flame": 5,
        "Carrot": 1,
        "Toad": 1,
        "Hyper Hedgehog": 1,
        "Shiny Shell": 1,
        "Crow": 1,
        "Flame Badge": 1,
        "Amulet of Fortune": 1,
        "Snake": 1,
        "Amulet of Steel": 1,
        "Amulet of Alchemy": 1,
        "Flawed Topaz": 1,
        "Present": 1,
        "Regular Amethyst": 1,
        "Stone Shoes": 1,
        "Flawless Sapphire": 1,
        "Cap of Resilience": 1,
        "Mrs. Struggles": 1
      }
    },
    {
      "roundIndex": 17,
      "result": "win",
      "gold": 324,
      "items": {
        "Fanny Pack": 1,
        "Puzzlebag of Energy": 1,
        "Puzzlebag of Ruin": 1,
        "Leather Bag": 4,
        "Potion Belt": 3,
        "Stamina Sack": 4,
        "Protective Purse": 1,
        "Holdall": 1,
        "Relic Case": 1,
        "Dragon Claws": 1,
        "Leaf Badge": 1,
        "Acorn Collar": 1,
        "Flame Badge": 1,
        "Present": 1,
        "Mrs. Struggles": 1,
        "Rope": 2,
        "Crow": 1,
        "Snake": 1,
        "Toad": 1,
        "Hyper Hedgehog": 1,
        "Badger Spirit Companion": 1,
        "Regular Amethyst": 1,
        "Stone Shoes": 1,
        "Ruby Egg": 1,
        "Amulet of Fortune": 1,
        "Hawk Rune": 1,
        "Fancy Fencing Rapier": 1,
        "Uniquely Unique": 1,
        "Cold Mirror": 1,
        "Burning Coal": 2,
        "Ruby Chonk": 1,
        "Flawless Ruby": 1,
        "Regular Ruby": 1,
        "Sun Shield": 1,
        "Cheese": 1,
        "Carrot": 1,
        "Amulet of Steel": 1,
        "Amulet of the Wild": 1,
        "Flawless Sapphire": 1,
        "Cap of Resilience": 1
      }
    },
    {
      "roundIndex": 18,
      "result": "win",
      "gold": 344,
      "items": {
        "Fanny Pack": 2,
        "Puzzlebag of Energy": 1,
        "Puzzlebag of Ruin": 1,
        "Leather Bag": 4,
        "Potion Belt": 3,
        "Stamina Sack": 4,
        "Protective Purse": 1,
        "Relic Case": 1,
        "Holdall": 1,
        "Dragon Claws": 1,
        "Mrs. Struggles": 1,
        "Rope": 2,
        "Crow": 1,
        "Snake": 1,
        "Toad": 1,
        "Hyper Hedgehog": 1,
        "Badger Spirit Companion": 1,
        "Regular Amethyst": 1,
        "Stone Shoes": 1,
        "Ruby Egg": 1,
        "Uniquely Unique": 1,
        "Flawed Topaz": 1,
        "Burning Coal": 2,
        "Ruby Chonk": 1,
        "Cheese": 1,
        "Amulet of Steel": 1,
        "Amulet of the Wild": 1,
        "Flawless Sapphire": 1,
        "Cap of Resilience": 2,
        "Flawless Ruby": 1,
        "Regular Ruby": 1,
        "Sun Shield": 1,
        "Present": 1,
        "Hawk Rune": 1,
        "Fancy Fencing Rapier": 1,
        "Acorn Collar": 2,
        "Amulet of Fortune": 1,
        "Cold Mirror": 1,
        "Flame Badge": 1,
        "Stoned": 1,
        "Leaf Badge": 1
      }
    }
  ]
}