{
  "runId": "2025-09-28_20-52-40",
  "pageNo": 62,
  "matchIndex": 82,
  "matchIndexOnPage": 2,
  "rounds": [
    {
      "roundIndex": 1,
      "result": "loss",
      "gold": 44,
      "items": {
        "Storage Coffin": 1,
        "Leather Bag": 2,
        "Wooden Sword": 2,
        "Pocket Sand": 1,
        "Piggybank": 1,
        "Whetstone": 1,
        "Chipped Topaz": 1
      }
    },
    {
      "roundIndex": 2,
      "result": "win",
      "gold": 58,
      "items": {
        "Storage Coffin": 1,
        "Leather Bag": 3,
        "Piggybank": 2,
        "Wooden Sword": 1,
        "Chipped Topaz": 1,
        "Hero Sword": 1,
        "Pocket Sand": 1,
        "Shiny Shell": 1,
        "Healing Herbs": 1,
        "Stone": 1
      }
    },
    {
      "roundIndex": 3,
      "result": "loss",
      "gold": 79,
      "items": {
        "Storage Coffin": 1,
        "Leather Bag": 4,
        "Piggybank": 3,
        "Wooden Sword": 1,
        "Chipped Topaz": 1,
        "Hero Sword": 1,
        "Shiny Shell": 1,
        "Healing Herbs": 1,
        "Stone": 2,
        "Whetstone": 1,
        "Pocket Sand": 1,
        "Walrus Tusk": 1,
        "Smithing For Dummies": 1
      }
    },
    {
      "roundIndex": 4,
      "result": "win",
      "gold": 93,
      "items": {
        "Storage Coffin": 1,
        "Leather Bag": 5,
        "Piggybank": 4,
        "Wooden Sword": 1,
        "Chipped Topaz": 1,
        "Hero Sword": 1,
        "Stone": 2,
        "Whetstone": 2,
        "Pocket Sand": 1,
        "Smithing For Dummies": 1,
        "Leather Armor": 1,
        "Walrus Tusk": 1,
        "Shiny Shell": 1
      }
    },
    {
      "roundIndex": 5,
      "result": "win",
      "gold": 105,
      "items": {
        "Storage Coffin": 1,
        "Leather Bag": 5,
        "Fanny Pack": 1,
        "Piggybank": 4,
        "Wooden Sword": 1,
        "Stone": 3,
        "Pocket Sand": 1,
        "Smithing For Dummies": 1,
        "Leather Armor": 1,
        "Walrus Tusk": 1,
        "Shiny Shell": 1,
        "Chipped Topaz": 1,
        "Hero Longsword": 1,
        "Snowball": 2
      }
    },
    {
      "roundIndex": 6,
      "result": "win",
      "gold": 122,
      "items": {
        "Storage Coffin": 1,
        "Leather Bag": 5,
        "Fanny Pack": 2,
        "Stone": 3,
        "Smithing For Dummies": 1,
        "Leather Armor": 1,
        "Chipped Topaz": 1,
        "Hero Longsword": 1,
        "Piggybank": 3,
        "Snowball": 2,
        "Bag of Stones": 1,
        "Walrus Tusk": 1,
        "Pocket Sand": 1,
        "Wooden Sword": 1,
        "Prismatic Orb": 1,
        "Shiny Shell": 1
      }
    },
    {
      "roundIndex": 7,
      "result": "win",
      "gold": 137,
      "items": {
        "Storage Coffin": 1,
        "Leather Bag": 6,
        "Fanny Pack": 2,
        "Chipped Topaz": 1,
        "Hero Longsword": 1,
        "Piggybank": 4,
        "Stone": 3,
        "Snowball": 2,
        "Bag of Stones": 1,
        "Prismatic Sword": 1,
        "Holy Armor": 1,
        "Pocket Sand": 1,
        "Smithing For Dummies": 1,
        "Shiny Shell": 2,
        "Walrus Tusk": 1
      }
    },
    {
      "roundIndex": 8,
      "result": "win",
      "gold": 159,
      "items": {
        "Storage Coffin": 1,
        "Leather Bag": 6,
        "Fanny Pack": 3,
        "Chipped Topaz": 1,
        "Hero Longsword": 1,
        "Piggybank": 4,
        "Snowball": 2,
        "Bag of Stones": 1,
        "Stone": 2,
        "Prismatic Sword": 1,
        "Holy Armor": 1,
        "Pocket Sand": 1,
        "Shiny Shell": 2,
        "Nocturnal Lock Lifter": 1,
        "Health Potion": 1,
        "Gloves of Haste": 1,
        "Toad": 1,
        "Smithing For Dummies": 1
      }
    },
    {
      "roundIndex": 9,
      "result": "win",
      "gold": 167,
      "items": {
        "Storage Coffin": 1,
        "Leather Bag": 6,
        "Fanny Pack": 3,
        "Pocket Sand": 1,
        "Shelly": 1,
        "Piggybank": 4,
        "Chipped Topaz": 1,
        "Prismatic Sword": 1,
        "Healing Herbs": 1,
        "Stone": 2,
        "Heart Container": 1,
        "Smithing For Dummies": 1,
        "Shiny Shell": 1,
        "Holy Armor": 1,
        "Snowball": 2,
        "Toad": 1,
        "Gloves of Haste": 1,
        "Nocturnal Lock Lifter": 1,
        "Health Potion": 1,
        "Mana Orb": 1
      }
    },
    {
      "roundIndex": 10,
      "result": "win",
      "gold": 193,
      "items": {
        "Storage Coffin": 1,
        "Leather Bag": 7,
        "Fanny Pack": 3,
        "Pocket Sand": 1,
        "Shelly": 2,
        "Chipped Topaz": 1,
        "Prismatic Sword": 1,
        "Stone": 2,
        "Heart Container": 1,
        "Smithing For Dummies": 1,
        "Snowball": 2,
        "Gloves of Haste": 1,
        "Mana Orb": 1,
        "False Life": 1,
        "Holy Armor": 1,
        "Maneki-neko": 1,
        "Toad": 1,
        "Healing Herbs": 1,
        "Nocturnal Lock Lifter": 1,
        "Piggybank": 4,
        "Cap of Resilience": 1
      }
    },
    {
      "roundIndex": 11,
      "result": "win",
      "gold": 205,
      "items": {
        "Storage Coffin": 1,
        "Leather Bag": 7,
        "Fanny Pack": 4,
        "Pocket Sand": 1,
        "Shelly": 2,
        "Chipped Topaz": 1,
        "Prismatic Sword": 1,
        "Stone": 2,
        "Heart Container": 1,
        "Snowball": 1,
        "Gloves of Haste": 1,
        "False Life": 1,
        "Holy Armor": 1,
        "Maneki-neko": 1,
        "Toad": 1,
        "Healing Herbs": 1,
        "Nocturnal Lock Lifter": 1,
        "Piggybank": 4,
        "Cap of Resilience": 1,
        "Stone Skin Potion": 1,
        "Mana Orb": 1,
        "Glowing Crown": 1
      }
    },
    {
      "roundIndex": 12,
      "result": "win",
      "gold": 229,
      "items": {
        "Storage Coffin": 1,
        "Leather Bag": 7,
        "Fanny Pack": 5,
        "Pocket Sand": 1,
        "Shelly": 2,
        "Chipped Topaz": 1,
        "Prismatic Sword": 1,
        "Heart Container": 1,
        "Snowball": 1,
        "Gloves of Haste": 1,
        "False Life": 1,
        "Corrupted Crystal": 1,
        "Holy Armor": 1,
        "Healing Herbs": 1,
        "Piggybank": 4,
        "Stone": 2,
        "Smithing For Dummies": 1,
        "Glowing Crown": 1,
        "Maneki-neko": 2,
        "Mana Orb": 1,
        "Nocturnal Lock Lifter": 1,
        "Stone Helm": 1,
        "Box of Riches": 1
      }
    },
    {
      "roundIndex": 13,
      "result": "win",
      "gold": 245,
      "items": {
        "Leather Bag": 8,
        "Fanny Pack": 5,
        "Storage Coffin": 1,
        "Stamina Sack": 1,
        "Piggybank": 4,
        "Chipped Topaz": 1,
        "Prismatic Sword": 1,
        "Corrupted Armor": 1,
        "Corrupted Crystal": 1,
        "Glowing Crown": 2,
        "Shelly": 2,
        "Maneki-neko": 2,
        "Chipped Amethyst": 1,
        "Mana Orb": 1,
        "Nocturnal Lock Lifter": 1,
        "Smithing For Dummies": 1,
        "Gloves of Haste": 1,
        "Stone Helm": 1,
        "False Life": 1,
        "Box of Riches": 1,
        "Snowball": 1,
        "Pocket Sand": 1,
        "Bag of Stones": 1,
        "Stone": 2
      }
    },
    {
      "roundIndex": 14,
      "result": "loss",
      "gold": 261,
      "items": {
        "Leather Bag": 8,
        "Fanny Pack": 5,
        "Storage Coffin": 1,
        "Stamina Sack": 1,
        "Piggybank": 4,
        "Chipped Topaz": 1,
        "Flawed Sapphire": 2,
        "Prismatic Sword": 1,
        "Corrupted Armor": 1,
        "Corrupted Crystal": 1,
        "Glowing Crown": 2,
        "Shelly": 2,
        "Maneki-neko": 2,
        "Gloves of Haste": 1,
        "Stone Helm": 1,
        "False Life": 1,
        "Snowball": 1,
        "Stone": 2,
        "Sir Sand": 1,
        "Mana Orb": 1,
        "Chipped Amethyst": 1,
        "Smithing For Dummies": 1,
        "Box of Riches": 1,
        "Shield of Valor": 1,
        "Nocturnal Lock Lifter": 1
      }
    },
    {
      "roundIndex": 15,
      "result": "loss",
      "gold": 279,
      "items": {
        "Leather Bag": 8,
        "Fanny Pack": 5,
        "Storage Coffin": 1,
        "Stamina Sack": 2,
        "Piggybank": 4,
        "Chipped Topaz": 1,
        "Regular Sapphire": 1,
        "Prismatic Sword": 1,
        "Corrupted Armor": 1,
        "Corrupted Crystal": 1,
        "Glowing Crown": 2,
        "Shelly": 2,
        "Maneki-neko": 2,
        "Gloves of Haste": 1,
        "False Life": 1,
        "Snowball": 1,
        "Stone": 1,
        "Mana Orb": 1,
        "Chipped Amethyst": 1,
        "Smithing For Dummies": 1,
        "Box of Riches": 1,
        "Regular Ruby": 1,
        "Chipped Ruby": 2,
        "Shield of Valor": 1,
        "Nocturnal Lock Lifter": 1,
        "Stone Helm": 1,
        "Sir Sand": 1,
        "Blood Amulet": 1
      }
    },
    {
      "roundIndex": 16,
      "result": "win",
      "gold": 292,
      "items": {
        "Leather Bag": 8,
        "Fanny Pack": 5,
        "Storage Coffin": 1,
        "Stamina Sack": 2,
        "Piggybank": 4,
        "Chipped Topaz": 2,
        "Regular Sapphire": 1,
        "Prismatic Sword": 1,
        "Corrupted Armor": 1,
        "Glowing Crown": 2,
        "Shelly": 2,
        "Maneki-neko": 2,
        "Gloves of Haste": 2,
        "False Life": 1,
        "Snowball": 1,
        "Chipped Amethyst": 1,
        "Box of Riches": 1,
        "Regular Ruby": 1,
        "Flawed Ruby": 1,
        "Shield of Valor": 1,
        "Nocturnal Lock Lifter": 1,
        "Stone Helm": 1,
        "Sir Sand": 1,
        "Blood Amulet": 3,
        "Smithing For Dummies": 1,
        "Mana Orb": 1
      }
    },
    {
      "roundIndex": 17,
      "result": "win",
      "gold": 306,
      "items": {
        "Leather Bag": 8,
        "Fanny Pack": 5,
        "Storage Coffin": 1,
        "Stamina Sack": 2,
        "Protective Purse": 1,
        "Chipped Topaz": 2,
        "Regular Sapphire": 1,
        "Prismatic Sword": 1,
        "Corrupted Armor": 1,
        "Regular Amethyst": 1,
        "Glowing Crown": 2,
        "Shelly": 2,
        "Maneki-neko": 2,
        "False Life": 1,
        "Snowball": 1,
        "Chipped Amethyst": 1,
        "Box of Riches": 1,
        "Regular Ruby": 1,
        "Flawed Ruby": 1,
        "Shield of Valor": 1,
        "Nocturnal Lock Lifter": 1,
        "Stone Helm": 1,
        "Sir Sand": 1,
        "Blood Amulet": 1,
        "Piggybank": 2,
        "Smithing For Dummies": 1,
        "Mana Orb": 1,
        "Vampiric Gloves": 2,
        "Jynx torquilla": 1,
        "Heroic Potion": 1
      }
    },
    {
      "roundIndex": 18,
      "result": "win",
      "gold": 316,
      "items": {
        "Leather Bag": 8,
        "Fanny Pack": 5,
        "Storage Coffin": 1,
        "Stamina Sack": 2,
        "Protective Purse": 1,
        "Chipped Topaz": 4,
        "Regular Sapphire": 1,
        "Prismatic Sword": 1,
        "Chipped Amethyst": 1,
        "Corrupted Armor": 1,
        "Regular Amethyst": 1,
        "Glowing Crown": 2,
        "Shelly": 2,
        "Maneki-neko": 2,
        "False Life": 1,
        "Regular Ruby": 1,
        "Flawed Ruby": 1,
        "Shield of Valor": 1,
        "Nocturnal Lock Lifter": 1,
        "Blood Amulet": 1,
        "Smithing For Dummies": 1,
        "Mana Orb": 2,
        "Vampiric Gloves": 2,
        "Jynx torquilla": 1,
        "Box of Riches": 1,
        "Stone Helm": 1,
        "Heroic Potion": 2,
        "Sir Sand": 1,
        "Unstable Recombobulator": 1
      }
    }
  ]
}