{
  "matchIndex": 326,
  "rounds": [
    {
      "roundIndex": 1,
      "result": "win",
      "gold": 43,
      "items": {
        "Relic Case": 1,
        "Leather Bag": 3,
        "Stone": 1,
        "Walrus Tusk": 1,
        "Flute": 1,
        "Shiny Shell": 1,
        "Broom": 1,
        "Star of Courage": 1,
        "Chipped Amethyst": 1
      }
    },
    {
      "roundIndex": 2,
      "result": "win",
      "gold": 57,
      "items": {
        "Relic Case": 1,
        "Leather Bag": 4,
        "Shiny Shell": 1,
        "Star of Courage": 1,
        "Chipped Amethyst": 1,
        "Flute": 1,
        "Broom": 1,
        "Stone": 1,
        "Lump of Coal": 1,
        "Wooden Sword": 1,
        "Banana": 1,
        "Garlic": 1,
        "Walrus Tusk": 1
      }
    },
    {
      "roundIndex": 3,
      "result": "win",
      "gold": 68,
      "items": {
        "Relic Case": 1,
        "Leather Bag": 5,
        "Broom": 1,
        "Torch": 1,
        "Goobert": 1,
        "Flute": 1,
        "Garlic": 1,
        "Chipped Amethyst": 1,
        "Health Potion": 1,
        "Shiny Shell": 1,
        "False Life": 1,
        "Stone": 1
      }
    },
    {
      "roundIndex": 4,
      "result": "win",
      "gold": 75,
      "items": {
        "Relic Case": 1,
        "Leather Bag": 5,
        "Fanny Pack": 1,
        "Garlic": 1,
        "False Life": 1,
        "Torch": 1,
        "Shelly": 1,
        "Gloves of Haste": 1,
        "Walrus Tusk": 1,
        "Flute": 1,
        "Goobert": 1,
        "Chipped Amethyst": 1,
        "Stone": 1
      }
    },
    {
      "roundIndex": 5,
      "result": "loss",
      "gold": 85,
      "items": {
        "Relic Case": 1,
        "Leather Bag": 5,
        "Fanny Pack": 1,
        "Garlic": 1,
        "False Life": 1,
        "Torch": 1,
        "Shelly": 1,
        "Flute": 1,
        "Goobert": 1,
        "Chipped Amethyst": 1,
        "Claws of Attack": 1,
        "Ruby Egg": 1,
        "Stone": 1
      }
    },
    {
      "roundIndex": 6,
      "result": "loss",
      "gold": 90,
      "items": {
        "Relic Case": 1,
        "Leather Bag": 5,
        "Fanny Pack": 1,
        "Garlic": 1,
        "False Life": 1,
        "Shelly": 1,
        "Flute": 1,
        "Goobert": 1,
        "Chipped Amethyst": 1,
        "Claws of Attack": 1,
        "Ruby Egg": 1,
        "Stone": 1,
        "Burning Torch": 1,
        "Box of Riches": 1
      }
    },
    {
      "roundIndex": 7,
      "result": "loss",
      "gold": 101,
      "items": {
        "Relic Case": 1,
        "Leather Bag": 6,
        "Fanny Pack": 1,
        "False Life": 1,
        "Shelly": 1,
        "Flute": 1,
        "Chipped Amethyst": 1,
        "Claws of Attack": 1,
        "Burning Torch": 1,
        "Chipped Ruby": 1,
        "Ruby Whelp": 1,
        "Goobert": 1,
        "The Lovers": 1,
        "Garlic": 1,
        "Deck of Cards": 1,
        "Box of Riches": 1,
        "Stone": 1
      }
    },
    {
      "roundIndex": 8,
      "result": "win",
      "gold": 123,
      "items": {
        "Fanny Pack": 2,
        "Leather Bag": 6,
        "Relic Case": 1,
        "Toad": 1,
        "Ruby Whelp": 1,
        "Goobert": 1,
        "Chipped Ruby": 1,
        "Burning Torch": 1,
        "Chipped Emerald": 1,
        "Claws of Attack": 1,
        "Snake": 1,
        "Shelly": 1,
        "Box of Riches": 2,
        "False Life": 1,
        "Deck of Cards": 1,
        "The Lovers": 1,
        "Darkest Lotus": 1,
        "Chipped Amethyst": 1
      }
    },
    {
      "roundIndex": 9,
      "result": "win",
      "gold": 136,
      "items": {
        "Fanny Pack": 2,
        "Leather Bag": 6,
        "Relic Case": 1,
        "Toad": 1,
        "Chipped Emerald": 1,
        "Ruby Whelp": 1,
        "Snake": 1,
        "Goobert": 1,
        "Shelly": 1,
        "Chipped Ruby": 2,
        "Claws of Attack": 1,
        "Burning Torch": 1,
        "Deck of Cards": 1,
        "The Lovers": 1,
        "Darkest Lotus": 1,
        "False Life": 1,
        "Chipped Amethyst": 1,
        "Glowing Crown": 1,
        "Box of Riches": 2
      }
    },
    {
      "roundIndex": 10,
      "result": "win",
      "gold": 149,
      "items": {
        "Fanny Pack": 2,
        "Leather Bag": 7,
        "Relic Case": 1,
        "Toad": 1,
        "Chipped Amethyst": 2,
        "Ruby Whelp": 1,
        "Snake": 1,
        "Goobert": 1,
        "Shelly": 1,
        "Chipped Emerald": 2,
        "Claws of Attack": 1,
        "Burning Torch": 1,
        "Deck of Cards": 1,
        "The Lovers": 1,
        "Darkest Lotus": 1,
        "False Life": 1,
        "Time Melting": 1,
        "Box of Riches": 1,
        "Flawed Ruby": 1,
        "King Crown": 1,
        "Chipped Sapphire": 1,
        "Chipped Topaz": 1
      }
    },
    {
      "roundIndex": 11,
      "result": "win",
      "gold": 162,
      "items": {
        "Fanny Pack": 2,
        "Leather Bag": 8,
        "Relic Case": 1,
        "Toad": 2,
        "Snake": 1,
        "Flawed Emerald": 1,
        "Claws of Attack": 1,
        "Chipped Topaz": 2,
        "Burning Torch": 1,
        "Flawed Ruby": 1,
        "Flawed Amethyst": 1,
        "King Goobert": 1,
        "False Life": 1,
        "Deck of Cards": 1,
        "Shelly": 1,
        "Ruby Whelp": 1,
        "Time Melting": 1,
        "Box of Riches": 1,
        "The Lovers": 1,
        "White-Eyes Blue Dragon": 1,
        "Holo Fire Lizard": 1
      }
    },
    {
      "roundIndex": 12,
      "result": "loss",
      "gold": 177,
      "items": {
        "Fanny Pack": 3,
        "Leather Bag": 8,
        "Relic Case": 1,
        "Toad": 2,
        "Snake": 1,
        "Claws of Attack": 1,
        "Burning Torch": 1,
        "Flawed Ruby": 1,
        "Flawed Amethyst": 1,
        "King Goobert": 1,
        "Shelly": 1,
        "Chipped Topaz": 1,
        "Flawed Emerald": 1,
        "Ruby Chonk": 1,
        "Deck of Cards": 1,
        "Chipped Amethyst": 1,
        "The Lovers": 1,
        "White-Eyes Blue Dragon": 1,
        "Time Melting": 1,
        "Box of Riches": 1,
        "Holo Fire Lizard": 1,
        "False Life": 1,
        "Cap of Resilience": 1
      }
    },
    {
      "roundIndex": 13,
      "result": "win",
      "gold": 194,
      "items": {
        "Fanny Pack": 3,
        "Leather Bag": 9,
        "Relic Case": 1,
        "Toad": 2,
        "Snake": 1,
        "Flawed Emerald": 1,
        "Claws of Attack": 1,
        "Burning Torch": 1,
        "Flawed Ruby": 1,
        "Flawed Amethyst": 1,
        "King Goobert": 1,
        "Shelly": 1,
        "Regular Topaz": 1,
        "Ruby Chonk": 1,
        "Chipped Amethyst": 1,
        "Time Melting": 1,
        "Box of Riches": 1,
        "False Life": 1,
        "Deck of Cards": 1,
        "The Lovers": 1,
        "White-Eyes Blue Dragon": 1,
        "Holo Fire Lizard": 1,
        "Cap of Resilience": 1,
        "Ruby Egg": 1
      }
    },
    {
      "roundIndex": 14,
      "result": "win",
      "gold": 211,
      "items": {
        "Fanny Pack": 3,
        "Leather Bag": 10,
        "Relic Case": 1,
        "Toad": 2,
        "Snake": 1,
        "Flawed Emerald": 1,
        "Claws of Attack": 1,
        "Burning Torch": 1,
        "Flawed Ruby": 1,
        "Flawed Amethyst": 1,
        "King Goobert": 1,
        "Shelly": 1,
        "Regular Topaz": 1,
        "Ruby Chonk": 1,
        "Chipped Amethyst": 1,
        "Box of Riches": 1,
        "Deck of Cards": 1,
        "The Lovers": 1,
        "Holo Fire Lizard": 2,
        "Ruby Egg": 1,
        "Chipped Emerald": 1,
        "Time Melting": 1,
        "Cap of Resilience": 2,
        "False Life": 1,
        "White-Eyes Blue Dragon": 1
      }
    },
    {
      "roundIndex": 15,
      "result": "win",
      "gold": 222,
      "items": {
        "Fanny Pack": 3,
        "Leather Bag": 10,
        "Relic Case": 1,
        "Protective Purse": 1,
        "Toad": 2,
        "Snake": 1,
        "Flawed Emerald": 1,
        "Claws of Attack": 1,
        "Chipped Emerald": 1,
        "Burning Torch": 1,
        "Flawed Ruby": 2,
        "King Goobert": 1,
        "Shelly": 1,
        "Regular Topaz": 1,
        "Ruby Chonk": 1,
        "Chipped Amethyst": 2,
        "Box of Riches": 1,
        "Flawed Amethyst": 1,
        "Cap of Resilience": 2,
        "Holo Fire Lizard": 2,
        "The Fool": 1,
        "Deck of Cards": 1,
        "White-Eyes Blue Dragon": 1,
        "Ruby Whelp": 1,
        "Jimbo": 1,
        "Time Melting": 1,
        "False Life": 1,
        "Chipped Ruby": 1
      }
    },
    {
      "roundIndex": 16,
      "result": "win",
      "gold": 250,
      "items": {
        "Fanny Pack": 4,
        "Leather Bag": 10,
        "Relic Case": 1,
        "Protective Purse": 2,
        "Toad": 2,
        "Shelly": 1,
        "Time Melting": 1,
        "Flawed Amethyst": 2,
        "Cap of Resilience": 2,
        "Flawed Emerald": 1,
        "Regular Topaz": 1,
        "Ruby Chonk": 2,
        "Chipped Sapphire": 1,
        "Claws of Attack": 1,
        "Chipped Emerald": 1,
        "Burning Torch": 1,
        "Snake": 1,
        "Perfect Ruby": 1,
        "Regular Ruby": 1,
        "King Goobert": 1,
        "Deck of Cards": 1,
        "The Fool": 1,
        "Holo Fire Lizard": 1,
        "White-Eyes Blue Dragon": 1,
        "Jimbo": 1,
        "Chipped Ruby": 1,
        "Mana Orb": 1,
        "False Life": 1,
        "Box of Riches": 1
      }
    },
    {
      "roundIndex": 17,
      "result": "loss",
      "gold": 264,
      "items": {
        "Fanny Pack": 4,
        "Leather Bag": 10,
        "Relic Case": 1,
        "Protective Purse": 2,
        "Toad": 2,
        "Time Melting": 1,
        "Flawed Amethyst": 2,
        "Cap of Resilience": 2,
        "Flawed Emerald": 1,
        "Regular Topaz": 1,
        "Ruby Chonk": 2,
        "Chipped Sapphire": 2,
        "Claws of Attack": 1,
        "Burning Torch": 1,
        "Snake": 1,
        "Perfect Ruby": 1,
        "Regular Ruby": 1,
        "King Goobert": 1,
        "Chipped Emerald": 1,
        "Deck of Cards": 1,
        "The Fool": 1,
        "Holo Fire Lizard": 1,
        "White-Eyes Blue Dragon": 1,
        "Mana Orb": 1,
        "Jynx torquilla": 1,
        "Chipped Ruby": 1,
        "Unsettling Presence": 1,
        "Shelly": 1,
        "False Life": 1,
        "Box of Riches": 1
      }
    },
    {
      "roundIndex": 18,
      "result": "win",
      "gold": 275,
      "items": {
        "Fanny Pack": 4,
        "Leather Bag": 10,
        "Relic Case": 1,
        "Protective Purse": 2,
        "Potion Belt": 1,
        "Toad": 2,
        "Time Melting": 1,
        "Flawed Amethyst": 2,
        "Cap of Resilience": 2,
        "Flawed Emerald": 1,
        "Regular Topaz": 1,
        "Ruby Chonk": 2,
        "Flawed Sapphire": 1,
        "Claws of Attack": 1,
        "Burning Torch": 1,
        "Snake": 1,
        "Chipped Emerald": 1,
        "Deck of Cards": 1,
        "The Fool": 1,
        "Holo Fire Lizard": 1,
        "White-Eyes Blue Dragon": 1,
        "Jynx torquilla": 1,
        "Shelly": 1,
        "Unsettling Presence": 1,
        "Mana Orb": 1,
        "Wolpertinger": 1,
        "False Life": 1,
        "Perfect Ruby": 1,
        "Regular Ruby": 1,
        "King Goobert": 1
      }
    }
  ]
}