{
  "matchIndex": 228,
  "rounds": [
    {
      "roundIndex": 1,
      "result": "loss",
      "gold": 41,
      "items": {
        "Leather Bag": 2,
        "Relic Case": 1,
        "Broom": 1,
        "Wooden Sword": 1,
        "Amulet of Darkness": 1,
        "Healing Herbs": 1,
        "Whetstone": 1
      }
    },
    {
      "roundIndex": 2,
      "result": "win",
      "gold": 54,
      "items": {
        "Leather Bag": 3,
        "Relic Case": 1,
        "Broom": 1,
        "Amulet of Darkness": 1,
        "Leather Armor": 1,
        "Hero Sword": 1,
        "Healing Herbs": 1,
        "Garlic": 1
      }
    },
    {
      "roundIndex": 3,
      "result": "win",
      "gold": 69,
      "items": {
        "Leather Bag": 4,
        "Relic Case": 1,
        "Broom": 1,
        "Amulet of Darkness": 1,
        "Leather Armor": 1,
        "Hero Sword": 1,
        "Healing Herbs": 1,
        "Garlic": 1,
        "Stone Skin Potion": 1,
        "Stoned": 1
      }
    },
    {
      "roundIndex": 4,
      "result": "win",
      "gold": 76,
      "items": {
        "Leather Bag": 5,
        "Relic Case": 1,
        "Broom": 1,
        "Amulet of Darkness": 1,
        "Leather Armor": 2,
        "Hero Sword": 1,
        "Garlic": 1,
        "Stone Skin Potion": 1,
        "Stoned": 1
      }
    },
    {
      "roundIndex": 5,
      "result": "win",
      "gold": 93,
      "items": {
        "Leather Bag": 5,
        "Relic Case": 1,
        "Stamina Sack": 1,
        "Broom": 1,
        "Amulet of Darkness": 1,
        "Leather Armor": 2,
        "Hero Sword": 1,
        "Stoned": 1,
        "Stone Skin Potion": 1,
        "Pestilence Flask": 1,
        "Fly Agaric": 1,
        "Healing Herbs": 1
      }
    },
    {
      "roundIndex": 6,
      "result": "loss",
      "gold": 103,
      "items": {
        "Leather Bag": 5,
        "Relic Case": 1,
        "Stamina Sack": 2,
        "Broom": 1,
        "Amulet of Darkness": 1,
        "Hero Sword": 1,
        "Stoned": 1,
        "Garlic": 1,
        "Leather Armor": 2,
        "Strong Pestilence Flask": 1,
        "Stone Skin Potion": 1,
        "Demonic Flask": 1
      }
    },
    {
      "roundIndex": 7,
      "result": "win",
      "gold": 114,
      "items": {
        "Leather Bag": 5,
        "Stamina Sack": 3,
        "Relic Case": 1,
        "Stoned": 1,
        "Broom": 1,
        "Leather Armor": 2,
        "Garlic": 2,
        "Hero Sword": 1,
        "Amulet of Darkness": 1,
        "Strong Pestilence Flask": 1,
        "Demonic Flask": 1,
        "Stone Skin Potion": 1,
        "Health Potion": 1
      }
    },
    {
      "roundIndex": 8,
      "result": "win",
      "gold": 140,
      "items": {
        "Leather Bag": 5,
        "Stamina Sack": 3,
        "Relic Case": 1,
        "Protective Purse": 1,
        "Stoned": 1,
        "Leather Armor": 2,
        "Amulet of Darkness": 1,
        "Demonic Flask": 1,
        "Stone Skin Potion": 1,
        "Health Potion": 1,
        "Fancy Fencing Rapier": 1,
        "Cursed Dagger": 1,
        "Hero Sword": 1,
        "Garlic": 1,
        "Strong Pestilence Flask": 1,
        "Blood Amulet": 1
      }
    },
    {
      "roundIndex": 9,
      "result": "loss",
      "gold": 143,
      "items": {
        "Leather Bag": 5,
        "Relic Case": 1,
        "Stamina Sack": 3,
        "Protective Purse": 1,
        "Strong Pestilence Flask": 1,
        "Amulet of Darkness": 1,
        "Death Scythe": 1,
        "Cursed Dagger": 1,
        "Stone Skin Potion": 2,
        "Demonic Flask": 1,
        "Health Potion": 1,
        "Vampiric Armor": 1,
        "Leather Armor": 1,
        "Leather Boots": 1,
        "Stoned": 1
      }
    },
    {
      "roundIndex": 10,
      "result": "win",
      "gold": 156,
      "items": {
        "Leather Bag": 6,
        "Relic Case": 1,
        "Stamina Sack": 3,
        "Protective Purse": 2,
        "Strong Pestilence Flask": 1,
        "Amulet of Darkness": 1,
        "Death Scythe": 1,
        "Cursed Dagger": 1,
        "Stone Skin Potion": 2,
        "Demonic Flask": 1,
        "Health Potion": 1,
        "Vampiric Armor": 1,
        "Stoned": 1,
        "Full Body Protection": 1,
        "Divine Potion": 1,
        "Leather Boots": 1,
        "Blueberries": 1
      }
    },
    {
      "roundIndex": 11,
      "result": "win",
      "gold": 170,
      "items": {
        "Leather Bag": 6,
        "Relic Case": 1,
        "Stamina Sack": 3,
        "Protective Purse": 2,
        "Strong Pestilence Flask": 1,
        "Amulet of Darkness": 1,
        "Death Scythe": 1,
        "Cursed Dagger": 1,
        "Stone Skin Potion": 2,
        "Demonic Flask": 1,
        "Health Potion": 1,
        "Vampiric Armor": 1,
        "Stoned": 1,
        "Full Body Protection": 1,
        "Corrupted Crystal": 1,
        "Cap of Resilience": 1,
        "Winged Boots": 1,
        "Blueberries": 1
      }
    },
    {
      "roundIndex": 12,
      "result": "loss",
      "gold": 179,
      "items": {
        "Stamina Sack": 3,
        "Relic Case": 1,
        "Leather Bag": 7,
        "Protective Purse": 2,
        "Death Scythe": 1,
        "Amulet of Darkness": 1,
        "Cursed Dagger": 1,
        "Stoned": 1,
        "Vampiric Armor": 1,
        "Pestilence Flask": 1,
        "Strong Pestilence Flask": 1,
        "Strong Demonic Flask": 1,
        "Health Potion": 1,
        "Stone Skin Potion": 2,
        "Full Body Protection": 1,
        "Winged Boots": 1,
        "Cap of Resilience": 1
      }
    },
    {
      "roundIndex": 13,
      "result": "win",
      "gold": 195,
      "items": {
        "Leather Bag": 7,
        "Stamina Sack": 3,
        "Relic Case": 1,
        "Protective Purse": 2,
        "Death Scythe": 1,
        "Fly Agaric": 1,
        "Pestilence Flask": 1,
        "Stone Skin Potion": 3,
        "Strong Pestilence Flask": 1,
        "Stoned": 1,
        "Strong Demonic Flask": 1,
        "Health Potion": 1,
        "Cursed Dagger": 1,
        "Cap of Resilience": 1,
        "Full Body Protection": 1,
        "Pineapple": 1,
        "Amulet of Darkness": 1,
        "Winged Boots": 1,
        "Vampiric Armor": 1
      }
    },
    {
      "roundIndex": 14,
      "result": "win",
      "gold": 211,
      "items": {
        "Stamina Sack": 3,
        "Relic Case": 1,
        "Leather Bag": 8,
        "Protective Purse": 2,
        "Death Scythe": 2,
        "Strong Pestilence Flask": 2,
        "Stone Skin Potion": 3,
        "Strong Demonic Flask": 1,
        "Health Potion": 1,
        "Cursed Dagger": 1,
        "Vampiric Armor": 1,
        "Full Body Protection": 1,
        "Winged Boots": 1,
        "Cap of Resilience": 1,
        "Pineapple": 1,
        "Amulet of Darkness": 1,
        "Stoned": 1
      }
    },
    {
      "roundIndex": 15,
      "result": "win",
      "gold": 226,
      "items": {
        "Stamina Sack": 3,
        "Relic Case": 1,
        "Leather Bag": 9,
        "Protective Purse": 2,
        "Death Scythe": 2,
        "Customer Card": 1,
        "Strong Demonic Flask": 1,
        "Health Potion": 1,
        "Demonic Flask": 1,
        "Strong Pestilence Flask": 2,
        "Amulet of Darkness": 1,
        "Stone Skin Potion": 3,
        "Cursed Dagger": 1,
        "Vampiric Armor": 1,
        "Full Body Protection": 1,
        "Winged Boots": 1,
        "Corrupted Crystal": 1,
        "Cap of Resilience": 1,
        "Stoned": 1
      }
    },
    {
      "roundIndex": 16,
      "result": "win",
      "gold": 241,
      "items": {
        "Stamina Sack": 3,
        "Relic Case": 1,
        "Leather Bag": 9,
        "Protective Purse": 4,
        "Death Scythe": 2,
        "Customer Card": 1,
        "Strong Demonic Flask": 1,
        "Health Potion": 1,
        "Demonic Flask": 1,
        "Strong Pestilence Flask": 2,
        "Amulet of Darkness": 1,
        "Stone Skin Potion": 3,
        "Cursed Dagger": 1,
        "Vampiric Armor": 1,
        "Full Body Protection": 1,
        "Stoned": 1,
        "Cap of Discomfort": 1,
        "Snowball": 2,
        "Winged Boots": 1,
        "Fly Agaric": 1
      }
    },
    {
      "roundIndex": 17,
      "result": "win",
      "gold": 256,
      "items": {
        "Stamina Sack": 4,
        "Relic Case": 1,
        "Leather Bag": 9,
        "Protective Purse": 4,
        "Death Scythe": 2,
        "Strong Demonic Flask": 1,
        "Health Potion": 1,
        "Demonic Flask": 2,
        "Strong Pestilence Flask": 2,
        "Amulet of Darkness": 1,
        "Stone Skin Potion": 3,
        "Vampiric Armor": 1,
        "Cap of Discomfort": 1,
        "Snowball": 2,
        "Fly Agaric": 2,
        "Full Body Protection": 1,
        "Winged Boots": 1,
        "Customer Card": 1,
        "Cursed Dagger": 1,
        "Stoned": 1
      }
    },
    {
      "roundIndex": 18,
      "result": "win",
      "gold": 269,
      "items": {
        "Stamina Sack": 4,
        "Relic Case": 1,
        "Leather Bag": 9,
        "Protective Purse": 4,
        "Death Scythe": 2,
        "Demonic Flask": 2,
        "Strong Pestilence Flask": 2,
        "Amulet of Darkness": 1,
        "Stone Skin Potion": 3,
        "Cursed Dagger": 1,
        "Vampiric Armor": 1,
        "Full Body Protection": 1,
        "Winged Boots": 1,
        "Cap of Discomfort": 1,
        "Maneki-neko": 1,
        "Doom Cap": 1,
        "Fly Agaric": 1,
        "Snowball": 2,
        "Strong Demonic Flask": 1,
        "Health Potion": 1,
        "Stoned": 1
      }
    }
  ]
}