{
  "matchIndex": 292,
  "rounds": [
    {
      "roundIndex": 1,
      "result": "loss",
      "gold": 39,
      "items": {
        "Relic Case": 1,
        "Stamina Sack": 1,
        "Leather Bag": 1,
        "Pan": 1,
        "Shiny Shell": 1,
        "Piggybank": 1,
        "Amulet of Energy": 1,
        "Banana": 1
      }
    },
    {
      "roundIndex": 2,
      "result": "loss",
      "gold": 47,
      "items": {
        "Relic Case": 1,
        "Leather Bag": 2,
        "Stamina Sack": 1,
        "Broom": 1,
        "Pan": 1,
        "Amulet of Energy": 1,
        "Banana": 1,
        "Garlic": 1,
        "Piggybank": 1
      }
    },
    {
      "roundIndex": 3,
      "result": "win",
      "gold": 63,
      "items": {
        "Relic Case": 1,
        "Leather Bag": 3,
        "Stamina Sack": 1,
        "Banana": 1,
        "Shovel": 1,
        "Wooden Sword": 1,
        "Whetstone": 1,
        "Amulet of Energy": 1,
        "Leather Armor": 1,
        "Piggybank": 1
      }
    },
    {
      "roundIndex": 4,
      "result": "loss",
      "gold": 85,
      "items": {
        "Relic Case": 1,
        "Leather Bag": 4,
        "Stamina Sack": 1,
        "Corrupted Crystal": 1,
        "Shovel": 1,
        "Hero Sword": 1,
        "Amulet of Energy": 1,
        "Bag of Stones": 1,
        "Leather Armor": 1,
        "Stone": 1,
        "Banana": 1,
        "Piggybank": 1,
        "Smelly Wall": 1,
        "Shiny Shell": 1
      }
    },
    {
      "roundIndex": 5,
      "result": "win",
      "gold": 95,
      "items": {
        "Relic Case": 1,
        "Leather Bag": 4,
        "Stamina Sack": 1,
        "Fanny Pack": 1,
        "Bag of Stones": 1,
        "Lump of Coal": 1,
        "Leather Armor": 1,
        "Stone": 2,
        "Hero Sword": 1,
        "Corrupted Crystal": 1,
        "Shovel": 1,
        "Amulet of Energy": 1,
        "Piggybank": 1,
        "Banana": 1,
        "Stone Skin Potion": 1,
        "Smelly Wall": 1
      }
    },
    {
      "roundIndex": 6,
      "result": "win",
      "gold": 112,
      "items": {
        "Relic Case": 1,
        "Leather Bag": 4,
        "Stamina Sack": 2,
        "Fanny Pack": 1,
        "Bag of Stones": 1,
        "Stone": 2,
        "Corrupted Crystal": 1,
        "Hero Sword": 1,
        "Amulet of Energy": 1,
        "Piggybank": 1,
        "Banana": 1,
        "Smelly Wall": 1,
        "Lump of Coal": 1,
        "Stone Armor": 1,
        "Ripsaw Blade": 1,
        "Stone Skin Potion": 1,
        "Customer Card": 1
      }
    },
    {
      "roundIndex": 7,
      "result": "win",
      "gold": 122,
      "items": {
        "Relic Case": 1,
        "Leather Bag": 4,
        "Stamina Sack": 2,
        "Fanny Pack": 1,
        "Protective Purse": 2,
        "Bag of Stones": 1,
        "Stone": 2,
        "Corrupted Crystal": 1,
        "Hero Sword": 1,
        "Amulet of Energy": 1,
        "Piggybank": 1,
        "Banana": 1,
        "Smelly Wall": 1,
        "Lump of Coal": 1,
        "Stone Armor": 1,
        "Ripsaw Blade": 1,
        "Customer Card": 1,
        "Health Potion": 1,
        "Stone Skin Potion": 1,
        "Blueberries": 1
      }
    },
    {
      "roundIndex": 8,
      "result": "loss",
      "gold": 134,
      "items": {
        "Leather Bag": 4,
        "Stamina Sack": 3,
        "Relic Case": 1,
        "Fanny Pack": 1,
        "Protective Purse": 2,
        "Lump of Coal": 1,
        "Stone Armor": 1,
        "Corrupted Crystal": 1,
        "Ripsaw Blade": 1,
        "Amulet of Energy": 1,
        "Cauldron": 1,
        "Health Potion": 2,
        "Stone Skin Potion": 1,
        "Blueberries": 1,
        "Piggybank": 1,
        "Customer Card": 1,
        "Banana": 1,
        "Box of Riches": 1,
        "Smelly Wall": 1
      }
    },
    {
      "roundIndex": 9,
      "result": "win",
      "gold": 148,
      "items": {
        "Leather Bag": 4,
        "Stamina Sack": 3,
        "Relic Case": 1,
        "Fanny Pack": 1,
        "Protective Purse": 2,
        "Potion Belt": 1,
        "Stone Armor": 1,
        "Amulet of Energy": 1,
        "Cauldron": 1,
        "Piggybank": 1,
        "Corrupted Crystal": 1,
        "Death Scythe": 1,
        "Pestilence Flask": 1,
        "Strong Stone Skin Potion": 1,
        "Health Potion": 1,
        "Mana Potion": 1,
        "Banana": 1,
        "Customer Card": 1,
        "Smelly Wall": 1,
        "Box of Riches": 1
      }
    },
    {
      "roundIndex": 10,
      "result": "win",
      "gold": 170,
      "items": {
        "Leather Bag": 4,
        "Relic Case": 1,
        "Stamina Sack": 3,
        "Fanny Pack": 2,
        "Protective Purse": 3,
        "Potion Belt": 1,
        "Stone Armor": 1,
        "Cauldron": 1,
        "Corrupted Crystal": 1,
        "Death Scythe": 1,
        "Piggybank": 1,
        "Cap of Resilience": 1,
        "Strong Pestilence Flask": 1,
        "Strong Stone Skin Potion": 1,
        "Health Potion": 1,
        "Mana Potion": 1,
        "Amulet of Alchemy": 1,
        "Heavy Drinking": 1,
        "Amulet of Energy": 1,
        "Smelly Wall": 1,
        "Banana": 1,
        "Box of Riches": 1
      }
    },
    {
      "roundIndex": 11,
      "result": "win",
      "gold": 191,
      "items": {
        "Leather Bag": 4,
        "Relic Case": 1,
        "Stamina Sack": 3,
        "Fanny Pack": 2,
        "Protective Purse": 4,
        "Potion Belt": 1,
        "Chipped Amethyst": 1,
        "Stone Armor": 1,
        "Cauldron": 1,
        "Death Scythe": 1,
        "Piggybank": 1,
        "Strong Pestilence Flask": 1,
        "Strong Stone Skin Potion": 1,
        "Health Potion": 1,
        "Heavy Drinking": 1,
        "Amulet of Energy": 1,
        "Smelly Wall": 1,
        "Banana": 1,
        "Strong Mana Potion": 1,
        "Corrupted Crystal": 1,
        "Cap of Discomfort": 1,
        "Customer Card": 1,
        "Amulet of Alchemy": 2,
        "Box of Riches": 1
      }
    },
    {
      "roundIndex": 12,
      "result": "loss",
      "gold": 206,
      "items": {
        "Leather Bag": 4,
        "Relic Case": 1,
        "Stamina Sack": 4,
        "Fanny Pack": 3,
        "Potion Belt": 1,
        "Protective Purse": 4,
        "Cauldron": 1,
        "Piggybank": 1,
        "Health Potion": 1,
        "Smelly Wall": 1,
        "Banana": 1,
        "Strong Mana Potion": 1,
        "Amulet of Alchemy": 2,
        "Box of Riches": 1,
        "Corrupted Crystal": 2,
        "Cap of Discomfort": 1,
        "Chipped Amethyst": 1,
        "Stone Armor": 1,
        "Death Scythe": 1,
        "Strong Pestilence Flask": 1,
        "Strong Stone Skin Potion": 1,
        "Heavy Drinking": 1,
        "Amulet of Energy": 1,
        "Customer Card": 1
      }
    },
    {
      "roundIndex": 13,
      "result": "win",
      "gold": 217,
      "items": {
        "Leather Bag": 4,
        "Relic Case": 1,
        "Stamina Sack": 4,
        "Fanny Pack": 3,
        "Potion Belt": 1,
        "Protective Purse": 4,
        "Cauldron": 1,
        "Piggybank": 1,
        "Health Potion": 1,
        "Amulet of Alchemy": 2,
        "Corrupted Crystal": 2,
        "Cap of Discomfort": 1,
        "Chipped Amethyst": 1,
        "Stone Armor": 1,
        "Death Scythe": 1,
        "Heavy Drinking": 1,
        "Customer Card": 1,
        "Strong Pestilence Flask": 1,
        "Strong Stone Skin Potion": 1,
        "Divine Potion": 1,
        "Smelly Wall": 1,
        "Amulet of Energy": 1,
        "Demonic Flask": 1,
        "Box of Riches": 1,
        "Strong Mana Potion": 1
      }
    },
    {
      "roundIndex": 14,
      "result": "win",
      "gold": 242,
      "items": {
        "Leather Bag": 4,
        "Relic Case": 1,
        "Stamina Sack": 4,
        "Fanny Pack": 4,
        "Potion Belt": 2,
        "Protective Purse": 4,
        "Cauldron": 1,
        "Health Potion": 1,
        "Amulet of Alchemy": 2,
        "Corrupted Crystal": 2,
        "Cap of Discomfort": 1,
        "Stone Armor": 1,
        "Death Scythe": 1,
        "Heavy Drinking": 1,
        "Customer Card": 1,
        "Strong Pestilence Flask": 1,
        "Strong Stone Skin Potion": 1,
        "Divine Potion": 1,
        "Smelly Wall": 1,
        "Amulet of Energy": 1,
        "Strong Demonic Flask": 1,
        "Demonic Flask": 1,
        "Box of Riches": 1,
        "Strong Mana Potion": 1,
        "Cap of Resilience": 1
      }
    },
    {
      "roundIndex": 15,
      "result": "win",
      "gold": 264,
      "items": {
        "Leather Bag": 4,
        "Relic Case": 1,
        "Stamina Sack": 4,
        "Fanny Pack": 4,
        "Potion Belt": 2,
        "Protective Purse": 5,
        "Cauldron": 1,
        "Customer Card": 1,
        "Strong Stone Skin Potion": 1,
        "Smelly Wall": 1,
        "Strong Demonic Flask": 2,
        "Box of Riches": 1,
        "Cap of Discomfort": 2,
        "Death Scythe": 1,
        "Heavy Drinking": 1,
        "Corrupted Crystal": 1,
        "Stone Armor": 1,
        "Strong Pestilence Flask": 1,
        "Amulet of Energy": 1,
        "Demonic Flask": 1,
        "Stone Skin Potion": 1,
        "Divine Potion": 1,
        "Strong Mana Potion": 1,
        "Amulet of Alchemy": 2,
        "Health Potion": 1
      }
    },
    {
      "roundIndex": 16,
      "result": "win",
      "gold": 290,
      "items": {
        "Leather Bag": 5,
        "Relic Case": 1,
        "Fanny Pack": 4,
        "Potion Belt": 2,
        "Stamina Sack": 4,
        "Protective Purse": 5,
        "Customer Card": 1,
        "Corrupted Crystal": 1,
        "Cap of Discomfort": 2,
        "Heavy Drinking": 1,
        "Chipped Amethyst": 1,
        "Stone Armor": 1,
        "Amulet of Energy": 1,
        "Amulet of Alchemy": 2,
        "Cauldron": 1,
        "Strong Demonic Flask": 3,
        "Strong Stone Skin Potion": 1,
        "Strong Pestilence Flask": 1,
        "Pestilence Flask": 1,
        "Stone Skin Potion": 1,
        "Divine Potion": 1,
        "Strong Mana Potion": 1,
        "Lightsaber": 1,
        "Death Scythe": 1,
        "Smelly Wall": 1,
        "Box of Riches": 1
      }
    },
    {
      "roundIndex": 17,
      "result": "win",
      "gold": 312,
      "items": {
        "Leather Bag": 5,
        "Stamina Sack": 4,
        "Protective Purse": 5,
        "Potion Belt": 2,
        "Fanny Pack": 5,
        "Relic Case": 1,
        "Divine Potion": 1,
        "Stone Skin Potion": 1,
        "Strong Mana Potion": 1,
        "Strong Stone Skin Potion": 1,
        "Strong Pestilence Flask": 2,
        "Death Scythe": 1,
        "Smelly Wall": 1,
        "Regular Sapphire": 1,
        "Darksaber": 1,
        "Heavy Drinking": 1,
        "Regular Amethyst": 1,
        "Cap of Discomfort": 2,
        "Strong Demonic Flask": 3,
        "Demonic Flask": 1,
        "Amulet of Alchemy": 2,
        "Chipped Amethyst": 1,
        "Chipped Topaz": 1,
        "Stone Armor": 1,
        "Amulet of Energy": 1,
        "Customer Card": 1,
        "Cauldron": 1,
        "Box of Riches": 1
      }
    },
    {
      "roundIndex": 18,
      "result": "win",
      "gold": 324,
      "items": {
        "Leather Bag": 3,
        "Potion Belt": 2,
        "Fanny Pack": 5,
        "Relic Case": 1,
        "Stamina Sack": 5,
        "Protective Purse": 6,
        "Strong Mana Potion": 1,
        "Strong Stone Skin Potion": 1,
        "Strong Pestilence Flask": 2,
        "Death Scythe": 1,
        "Smelly Wall": 1,
        "Regular Sapphire": 1,
        "Darksaber": 1,
        "Heavy Drinking": 1,
        "Strong Demonic Flask": 4,
        "Amulet of Alchemy": 2,
        "Stone Skin Potion": 2,
        "Divine Potion": 1,
        "Perfect Topaz": 1,
        "Stone Armor": 1,
        "Chipped Amethyst": 1,
        "Cap of Discomfort": 2,
        "Cauldron": 1,
        "Regular Amethyst": 1
      }
    }
  ]
}