{
  "runId": "2025-09-28_20-52-40",
  "pageNo": 64,
  "matchIndex": 130,
  "matchIndexOnPage": 10,
  "rounds": [
    {
      "roundIndex": 1,
      "result": "loss",
      "gold": 36,
      "items": {
        "Relic Case": 1,
        "Fanny Pack": 1,
        "Leather Bag": 1,
        "Hammer": 1,
        "Heroic Potion": 1,
        "Banana": 1
      }
    },
    {
      "roundIndex": 2,
      "result": "win",
      "gold": 51,
      "items": {
        "Relic Case": 1,
        "Leather Bag": 2,
        "Fanny Pack": 2,
        "Piggybank": 1,
        "Hammer": 1,
        "Strong Heroic Potion": 1,
        "Wooden Buckler": 1,
        "Star of Courage": 1
      }
    },
    {
      "roundIndex": 3,
      "result": "win",
      "gold": 66,
      "items": {
        "Relic Case": 1,
        "Leather Bag": 3,
        "Fanny Pack": 2,
        "Piggybank": 2,
        "Hammer": 1,
        "Strong Heroic Potion": 1,
        "Wooden Buckler": 1,
        "Enchanted Weapons": 1,
        "Deck of Cards": 1,
        "Star of Courage": 1
      }
    },
    {
      "roundIndex": 4,
      "result": "loss",
      "gold": 81,
      "items": {
        "Relic Case": 1,
        "Leather Bag": 4,
        "Fanny Pack": 2,
        "Hammer": 1,
        "Strong Heroic Potion": 1,
        "Enchanted Weapons": 1,
        "Piggybank": 2,
        "Star of Courage": 1,
        "Unstable Recombobulator": 1,
        "Bunch of Coins": 1,
        "Deck of Cards": 1
      }
    },
    {
      "roundIndex": 5,
      "result": "loss",
      "gold": 92,
      "items": {
        "Leather Bag": 5,
        "Fanny Pack": 4,
        "Relic Case": 1,
        "Star of Courage": 1,
        "Strong Heroic Potion": 1,
        "Hammer": 1,
        "Dagger": 1,
        "Blood Amulet": 1,
        "Enchanted Weapons": 1,
        "Health Potion": 1,
        "Piggybank": 2,
        "Deck of Cards": 1
      }
    },
    {
      "roundIndex": 6,
      "result": "win",
      "gold": 103,
      "items": {
        "Leather Bag": 5,
        "Fanny Pack": 4,
        "Relic Case": 1,
        "Star of Courage": 1,
        "Strong Heroic Potion": 1,
        "Hammer": 1,
        "Health Potion": 1,
        "Piggybank": 1,
        "Bloody Dagger": 1,
        "Dagger": 2,
        "Enchanted Weapons": 1,
        "Deck of Cards": 1,
        "Toad": 1
      }
    },
    {
      "roundIndex": 7,
      "result": "win",
      "gold": 114,
      "items": {
        "Leather Bag": 5,
        "Fanny Pack": 4,
        "Relic Case": 1,
        "Strong Heroic Potion": 1,
        "Hammer": 1,
        "Bloody Dagger": 1,
        "Dagger": 2,
        "Enchanted Weapons": 1,
        "Ruby Egg": 1,
        "Piggybank": 1,
        "Health Potion": 1,
        "Deck of Cards": 1,
        "Pestilence Flask": 1,
        "Star of Courage": 1
      }
    },
    {
      "roundIndex": 8,
      "result": "win",
      "gold": 141,
      "items": {
        "Leather Bag": 5,
        "Fanny Pack": 4,
        "Relic Case": 1,
        "Stamina Sack": 1,
        "Hammer": 1,
        "Bloody Dagger": 1,
        "Dagger": 2,
        "Enchanted Weapons": 1,
        "Ruby Egg": 1,
        "Star of Courage": 1,
        "Cursed Dagger": 1,
        "Poison Dagger": 1,
        "Strong Heroic Potion": 1,
        "Pestilence Flask": 1,
        "Blood Amulet": 1,
        "Deck of Cards": 1
      }
    },
    {
      "roundIndex": 9,
      "result": "win",
      "gold": 156,
      "items": {
        "Leather Bag": 5,
        "Fanny Pack": 4,
        "Relic Case": 1,
        "Stamina Sack": 1,
        "Corrupted Crystal": 1,
        "Hammer": 1,
        "Bloody Dagger": 2,
        "Enchanted Weapons": 1,
        "Star of Courage": 1,
        "Cursed Dagger": 1,
        "Poison Dagger": 2,
        "Snowball": 1,
        "Strong Heroic Potion": 1,
        "Ruby Whelp": 1,
        "White-Eyes Blue Dragon": 1,
        "Deck of Cards": 1
      }
    },
    {
      "roundIndex": 10,
      "result": "win",
      "gold": 172,
      "items": {
        "Leather Bag": 6,
        "Fanny Pack": 4,
        "Relic Case": 1,
        "Stamina Sack": 1,
        "Potion Belt": 1,
        "Protective Purse": 1,
        "Corrupted Crystal": 1,
        "Hammer": 1,
        "Bloody Dagger": 2,
        "Enchanted Weapons": 1,
        "Star of Courage": 1,
        "Cursed Dagger": 1,
        "Poison Dagger": 2,
        "Snowball": 1,
        "Deck of Cards": 1,
        "Ice Dragon": 1,
        "Strong Heroic Potion": 1,
        "Time Melting": 1
      }
    },
    {
      "roundIndex": 11,
      "result": "win",
      "gold": 184,
      "items": {
        "Leather Bag": 6,
        "Fanny Pack": 4,
        "Relic Case": 1,
        "Stamina Sack": 1,
        "Potion Belt": 1,
        "Protective Purse": 2,
        "Corrupted Crystal": 1,
        "Hammer": 1,
        "Bloody Dagger": 2,
        "Enchanted Weapons": 1,
        "Star of Courage": 1,
        "Cursed Dagger": 1,
        "Poison Dagger": 2,
        "Snowball": 1,
        "Deck of Cards": 1,
        "Ice Dragon": 1,
        "Strong Heroic Potion": 1,
        "Time Melting": 1,
        "White-Eyes Blue Dragon": 1,
        "Stable Recombobulator": 1
      }
    },
    {
      "roundIndex": 12,
      "result": "loss",
      "gold": 203,
      "items": {
        "Leather Bag": 6,
        "Fanny Pack": 4,
        "Relic Case": 1,
        "Potion Belt": 1,
        "Protective Purse": 2,
        "Stamina Sack": 1,
        "Corrupted Crystal": 1,
        "Hammer": 1,
        "Bloody Dagger": 2,
        "Enchanted Weapons": 1,
        "Cursed Dagger": 1,
        "Ice Dragon": 1,
        "Poison Dagger": 2,
        "Strong Heroic Potion": 1,
        "Time Melting": 1,
        "Leather Armor": 1,
        "Stable Recombobulator": 1,
        "Star of Courage": 1,
        "Deck of Cards": 1,
        "Ruby Egg": 1,
        "White-Eyes Blue Dragon": 1,
        "Leather Boots": 1
      }
    },
    {
      "roundIndex": 13,
      "result": "win",
      "gold": 219,
      "items": {
        "Leather Bag": 6,
        "Fanny Pack": 5,
        "Relic Case": 1,
        "Potion Belt": 1,
        "Protective Purse": 2,
        "Stamina Sack": 1,
        "Chipped Topaz": 1,
        "Corrupted Crystal": 1,
        "Hammer": 1,
        "Bloody Dagger": 2,
        "Enchanted Weapons": 1,
        "Cursed Dagger": 1,
        "Poison Dagger": 2,
        "Strong Heroic Potion": 1,
        "Stable Recombobulator": 1,
        "Star of Courage": 1,
        "Ruby Egg": 1,
        "Leather Boots": 1,
        "Piggybank": 1,
        "Time Melting": 1,
        "Ice Dragon": 1,
        "Flawed Amethyst": 1,
        "Cap of Resilience": 1,
        "Deck of Cards": 1,
        "White-Eyes Blue Dragon": 1,
        "Divine Potion": 1
      }
    },
    {
      "roundIndex": 14,
      "result": "win",
      "gold": 249,
      "items": {
        "Leather Bag": 7,
        "Fanny Pack": 5,
        "Relic Case": 1,
        "Potion Belt": 1,
        "Protective Purse": 2,
        "Stamina Sack": 1,
        "Chipped Topaz": 1,
        "Hammer": 1,
        "Bloody Dagger": 2,
        "Enchanted Weapons": 1,
        "Cursed Dagger": 1,
        "Poison Dagger": 2,
        "Strong Heroic Potion": 1,
        "Time Melting": 1,
        "Ice Dragon": 1,
        "Maneki-neko": 1,
        "Piggybank": 1,
        "Flawed Amethyst": 1,
        "Cap of Discomfort": 1,
        "Stable Recombobulator": 1,
        "Bag of Stones": 1,
        "Bunch of Coins": 1,
        "Ruby Whelp": 1,
        "Shiny Shell": 1,
        "Deck of Cards": 1,
        "White-Eyes Blue Dragon": 1,
        "Winged Boots": 1,
        "Twine": 1,
        "Star of Courage": 1
      }
    },
    {
      "roundIndex": 15,
      "result": "win",
      "gold": 272,
      "items": {
        "Leather Bag": 7,
        "Fanny Pack": 6,
        "Relic Case": 1,
        "Potion Belt": 1,
        "Protective Purse": 3,
        "Stamina Sack": 1,
        "Chipped Topaz": 1,
        "Hammer": 1,
        "Bloody Dagger": 2,
        "Enchanted Weapons": 1,
        "Cursed Dagger": 1,
        "Poison Dagger": 2,
        "Maneki-neko": 1,
        "Winged Boots": 1,
        "Star of Courage": 1,
        "Ice Dragon": 2,
        "Heart Container": 1,
        "Flawed Amethyst": 1,
        "Cap of Discomfort": 1,
        "Badger Spirit Companion": 1,
        "Stable Recombobulator": 1,
        "Time Melting": 1,
        "Strong Heroic Potion": 1,
        "Banana": 1,
        "Carrot": 1,
        "Twine": 1,
        "Mana Orb": 1,
        "Bunch of Coins": 1
      }
    },
    {
      "roundIndex": 16,
      "result": "win",
      "gold": 287,
      "items": {
        "Leather Bag": 7,
        "Fanny Pack": 7,
        "Relic Case": 1,
        "Potion Belt": 1,
        "Protective Purse": 4,
        "Stamina Sack": 2,
        "Chipped Topaz": 1,
        "Chipped Sapphire": 1,
        "Hammer": 1,
        "Bloody Dagger": 2,
        "Enchanted Weapons": 1,
        "Cursed Dagger": 1,
        "Poison Dagger": 2,
        "Maneki-neko": 1,
        "Star of Courage": 1,
        "Ice Dragon": 2,
        "Badger Spirit Companion": 1,
        "Twine": 1,
        "Mana Orb": 1,
        "Stable Recombobulator": 1,
        "Oil Lamp": 1,
        "Winged Boots": 2,
        "Time Melting": 1,
        "Flawed Amethyst": 1,
        "Cap of Discomfort": 1,
        "Piggybank": 1,
        "Banana": 1,
        "Carrot": 1,
        "Strong Heroic Potion": 1,
        "Shiny Shell": 1
      }
    },
    {
      "roundIndex": 17,
      "result": "loss",
      "gold": 312,
      "items": {
        "Leather Bag": 7,
        "Fanny Pack": 7,
        "Relic Case": 1,
        "Potion Belt": 1,
        "Protective Purse": 4,
        "Stamina Sack": 3,
        "Chipped Topaz": 1,
        "Regular Sapphire": 1,
        "Hammer": 1,
        "Bloody Dagger": 2,
        "Enchanted Weapons": 1,
        "Chipped Sapphire": 1,
        "Cursed Dagger": 1,
        "Poison Dagger": 2,
        "Maneki-neko": 1,
        "Star of Courage": 1,
        "Ice Dragon": 2,
        "Badger Spirit Companion": 1,
        "Mana Orb": 1,
        "Winged Boots": 2,
        "Flawed Amethyst": 1,
        "Cap of Discomfort": 1,
        "Banana": 1,
        "Carrot": 1,
        "Bunch of Coins": 1,
        "Vampiric Potion": 1,
        "Strong Heroic Potion": 1,
        "Broccoli": 1,
        "Blueberries": 1,
        "Time Melting": 1,
        "Deck of Cards": 1,
        "Dagger": 1,
        "Stable Recombobulator": 1
      }
    },
    {
      "roundIndex": 18,
      "result": "win",
      "gold": 318,
      "items": {
        "Leather Bag": 7,
        "Fanny Pack": 7,
        "Relic Case": 1,
        "Potion Belt": 1,
        "Protective Purse": 4,
        "Stamina Sack": 3,
        "Chipped Topaz": 1,
        "Regular Sapphire": 2,
        "Hammer": 1,
        "Bloody Dagger": 2,
        "Enchanted Weapons": 1,
        "Chipped Sapphire": 1,
        "Cursed Dagger": 1,
        "Poison Dagger": 2,
        "Maneki-neko": 1,
        "Star of Courage": 1,
        "Ice Dragon": 2,
        "Badger Spirit Companion": 1,
        "Mana Orb": 1,
        "Chipped Ruby": 1,
        "Winged Boots": 2,
        "Banana": 1,
        "Carrot": 1,
        "Broccoli": 1,
        "Blueberries": 2,
        "Time Melting": 1,
        "Stable Recombobulator": 1,
        "Spectral Dagger": 1,
        "Strong Heroic Potion": 1,
        "Vampiric Potion": 1,
        "Heroic Potion": 1,
        "Spell Scroll: Regrowth": 1,
        "Flawed Amethyst": 1,
        "Cap of Discomfort": 1
      }
    }
  ]
}